final/watchController/SevenSegDecoder.v
module SevenSegDecoder(
  input[3:0] number,
  output A, B, C, D, E, F, G
);

reg A,B,C,D,E,F,G;

//fix this to only combinational logic?
always @(number)
begin
  if  (number == 4'b0000)
  begin
    A = 1;
    B = 1;
    C = 1;
    D = 1;
    E = 1;
    F = 1;
    G = 0;
  end
  else if  (number == 4'b0001)
  begin
    A = 0;
    B = 1;
    C = 1;
    D = 0;
    E = 0;
    F = 0;
    G = 0;
  end
  else if  (number == 4'b0010)
  begin
    A = 1;
    B = 1;
    C = 0;
    D = 1;
    E = 1;
    F = 0;
    G = 1;
  end
  else if  (number == 4'b0011)
  begin
    A = 1;
    B = 1;
    C = 1;
    D = 1;
    E = 0;
    F = 0;
    G = 1;
  end
  else if  (number == 4'b0100)
  begin
    A = 0;
    B = 1;
    C = 1;
    D = 0;
    E = 0;
    F = 1;
    G = 1;
  end
  else if  (number == 4'b0101)
  begin
    A = 1;
    B = 0;
    C = 1;
    D = 1;
    E = 0;
    F = 1;
    G = 1;
  end
  else if  (number == 4'b0110)
  begin
    A = 1;
    B = 0;
    C = 1;
    D = 1;
    E = 1;
    F = 1;
    G = 1;
  end
  else if  (number == 4'b0111)
  begin
    A = 1;
    B = 1;
    C = 1;
    D = 0;
    E = 0;
    F = 1;
    G = 0;
  end
  else if  (number == 4'b1000)
  begin
    A = 1;
    B = 1;
    C = 1;
    D = 1;
    E = 1;
    F = 1;
    G = 1;
  end
  else if  (number == 4'b1001)
  begin
    A = 1;
    B = 1;
    C = 1;
    D = 1;
    E = 0;
    F = 1;
    G = 1;
  end
end 
endmodule

final/watchController/Mod2Counter.v
`ifndef MOD2_V
`define MOD2_V
module Mod2Counter(
  output reg[3:0] number,
  output reg cout,
  input start_resume,reset, stop, clk
);

reg [3:0] current, next;

parameter zero =4'b0000,
  one=4'b0001;
  //two=4'b0010,

always @(current or start_resume or reset or stop) 
begin
  if(start_resume==1 && current != one)
  begin
    if  (current == zero)
    begin
      cout = 1;
    end
    else
    begin
      cout = 0;
    end
    next=current + 1;
    number=current;
  end
  else if(start_resume==0)
  begin
    cout = 0;
    next=current;
    number=current;
  end
  else if(stop==1)
  begin
    cout = 0;
    next=current;
    number=current;
  end
  else if(reset==1) 
  begin
    cout = 0;
    next=zero;
    number=current;
  end

  //change this to for counter of different modulo
  if(current == one)
  begin
    next = zero;
    cout = 0;
    number = current;
  end

end

always @(posedge clk)
begin
  begin
    if(reset==1)
      current <= zero;
    else
      current <= next;
  end
end
endmodule
`endif

final/watchController/Mod13Counter.v
`ifndef MOD13_V
`define MOD13_V
//since modulo is expensive(is it?)
//do it manually
//first digit of hour display
//should have 24/12 mode input?????
module Mod13Counter(
  output reg[3:0] number,
  output reg cout,
  input start_resume,reset, stop, clk
);

reg [3:0] current, next;

parameter zero =4'b0000,
  one=4'b0001,
  two=4'b0010,
  three=4'b0011,
  four=4'b0100,
  five=4'b0101,
  six=4'b0110,
  seven=4'b0111,
  eight=4'b1000,
  nine=4'b1001,
  ten=4'b1010,
  eleven = 4'b1011,
  twelve = 4'b1100;
  

always @(current or start_resume or reset or stop) 
begin
  if(start_resume==1 && current != twelve)
  begin
    if  (current == zero)
    begin
      cout = 1;
    end
    else
    begin
      cout = 0;
    end
    next=current + 1;
	if(current == ten)
		number = zero;
	else if(current == eleven)
		number = one;
	else if(current == twelve)
		number = two;
	else
		number = current;
  end
  else if(start_resume==0)
  begin
    cout = 0;
    next=current;
    if(current == ten)
		number = zero;
	else if(current == eleven)
		number = one;
	else if(current == twelve)
		number = two;
	else
		number = current;
  end
  else if(stop==1)
  begin
    cout = 0;
    next=current;
    if(current == ten)
		number = zero;
	else if(current == eleven)
		number = one;
	else if(current == twelve)
		number = two;
	else
		number = current;
  end
  else if(reset==1) 
  begin
    cout = 0;
    next=zero;
    if(current == ten)
		number = zero;
	else if(current == eleven)
		number = one;
	else if(current == twelve)
		number = two;
	else
		number = current;
  end

  //change this to for counter of different modulo
  if(current == twelve)
  begin
    next = zero;
    cout = 0;
    if(current == ten)
		number = zero;
	else if(current == eleven)
		number = one;
	else if(current == twelve)
		number = two;
	else
		number = current;
  end

end

always @(posedge clk)
begin
  begin
    if(reset==1)
      current <= zero;
    else
      current <= next;
  end
end
endmodule
`endif

final/watchController/Mod6Counter.v
`ifndef MOD6_V
`define MOD6_V
module Mod6Counter(
  output reg[3:0] number,
  output reg cout,
  input start_resume,reset, stop, clk
);

reg [3:0] current, next;

parameter zero =4'b0000,
  one=4'b0001,
  two=4'b0010,
  three=4'b0011,
  four=4'b0100,
  five=4'b0101,
  six=4'b0110,
  seven=4'b0111,
  eight=4'b1000,
  nine=4'b1001;

always @(current or start_resume or reset or stop) 
begin
  if(start_resume==1 && current != nine)
  begin
    if  (current == zero)
    begin
      cout = 1;
    end
    else
    begin
      cout = 0;
    end
    next=current + 1;
    number=current;
  end
  else if(start_resume==0)
  begin
    cout = 0;
    next=current;
    number=current;
  end
  else if(stop==1)
  begin
    cout = 0;
    next=current;
    number=current;
  end
  else if(reset==1) 
  begin
    cout = 0;
    next=zero;
    number=current;
  end

  //change this to for counter of different modulo
  if(current == five)
  begin
    next = zero;
    cout = 0;
    number = current;
  end

end

always @(posedge clk)
begin
  begin
    if(reset==1)
      current <= zero;
    else
      current <= next;
  end
end
endmodule
`endif

final/watchController/Mod10Counter.v
`ifndef MOD10_V
`define MOD10_V
module Mod10Counter(
  output[3:0] number,
  output cout,
  input start_resume,reset, stop, clk
);

reg [3:0] current, next;
reg [3:0] number;
reg cout;

parameter zero =4'b0000,
  one=4'b0001,
  two=4'b0010,
  three=4'b0011,
  four=4'b0100,
  five=4'b0101,
  six=4'b0110,
  seven=4'b0111,
  eight=4'b1000,
  nine=4'b1001;

always @(current or start_resume or reset or stop) 
begin
  if(start_resume==1 && current != nine)
  begin
    if  (current == zero)
    begin
      cout = 1;
    end
    else
    begin
      cout = 0;
    end
    next=current + 1;
    number=current;
  end
  else if(start_resume==0)
  begin
    cout = 0;
    next=current;
    number=current;
  end
  else if(stop==1)
  begin
    cout = 0;
    next=current;
    number=current;
  end
  else if(reset==1) 
  begin
    cout = 0;
    next=zero;
    number=current;
  end

  //change this to for counter of different modulo
  if(current == nine)
  begin
    next = zero;
    cout = 0;
    number = current;
  end

end

always @(posedge clk)
begin
  begin
    if(reset==1)
      current <= zero;
    else
      current <= next;
  end
end
endmodule
`endif

final/watchController/Watch.v
`include "./Mod6Counter.v"
`include "./Mod10Counter.v"
`include "./Mod2Counter.v"//hour 1 digit
`include "./Mod13Counter.v" //hour 0 digit

//able to set time 
module Watch (
  output[3:0] hr1, hr0, min1, min0,
  input start_resume,reset, stop, clk, setTime
);

wire  hr1, hr0, min1, min0;
wire min1clk, h0clk, h1clk;

Mod10Counter Min0(min0,min1clk,start_resume,reset,stop,clk);
Mod6Counter Min1(min1,h0clk,start_resume,reset,stop,min1clk);
Mod13Counter Hr0(hr0,h1clk,start_resume,reset,stop,h0clk);
Mod2Counter Hr1(hr1,,start_resume,reset,stop,h1clk);
  
endmodule

final/watchController/StopWatch.v
`include "./Counter/Mod6Counter.v"
`include "./Counter/Mod10Counter.v"



module StopWatch(
  output[3:0] min0, sec1, sec0, milSec0,
  input start_resume,reset, stop, clk
);
wire min0,sec1,sec0,milSec0;

wire min0clk, sec1clk, sec0clk;


//devide the clk and put it as input.
Mod10Counter MIL0(milSec0, sec0clk, start_resume,reset,stop,clk);
Mod10Counter SEC0(sec0, sec1clk, start_resume,reset,stop,sec0clk);
Mod6Counter SEC1(sec1, min0clk, start_resume,reset,stop,sec1clk);
Mod10Counter MIN0(min0,,start_resume,reset,stop,min0clk);

endmodule

final/watchController/AlarmModule.v
//TODO get input from SetTime
module AlarmModule (
  output alarm,
  input[3:0] curHour1, curHour0, curMin1, curMin0, //read time every n's clk
  input alarmSet, alarmReset, clk
);
reg alarm;
reg[3:0] savMin0, savMin1, savHour0, savHour1; //save alarm time

always @(curMin0) //if curMin0 changes, everything changes
begin
  if  (
    savMin0 == curMin0   &&
    savMin1 == curMin1   &&
    savHour0 == curHour0 &&
    savHour1 == curHour1 
  ) 
  begin
    alarm = 1;
  end
  else 
  begin
    alarm = 0;
  end 
end

always @(posedge clk)
begin
  begin
    if(alarmReset==1)
    begin
      savMin0 <= 0;
      savMin1 <= 0;
      savHour0 <= 0;
      savHour1 <= 0;
    end 
    else if(alarmSet == 1)
    begin
      savMin0 <= curMin0;
      savMin1 <= curMin1;
      savHour0 <= curHour0;
      savHour1 <= curHour1;
    end 
  end
end


endmodule

final/settime/SetTime.v
//based on mode, should use diffrent modulous for time???
//NO! Alarm and clock use the same time scale.
//How should we return output?
module SetTime (
  output[3:0] h1, h0, m1, m0,
  input start, reset, nextDigit, up
);

reg h1, h0, m1, m0;
//wire current, next;
reg[1:0] currNum;
reg changeTime;

always @(posedge up or posedge reset)
begin
  begin
    if  (reset == 1)
    begin
      currNum <= 0;
      changeTime <= 0;
      h1 <= 0;
      h0 <= 0;
      m1 <= 0;
      m0 <= 0;
    end
    else if  (currNum == 3 && changeTime==1)
      h1 <= (h1 + 1)%2; //TODO should change this depending on time mode
    else if  (currNum == 2&& changeTime==1)
      h0 <= (h0 + 1)%10; //can use 10 modulous instead of 12 because there is not cout
    else if  (currNum == 1&& changeTime==1)
      m1 <= (m1 + 1)%6;
    else if  (currNum == 0&& changeTime==1)
      m0 <= (m0 + 1)%10;
  end
end

always @(posedge nextDigit)
begin
  begin
    if  (currNum == 3)
      currNum <= 0;
    else
      currNum <= currNum + 1;
  end
end

//odd number of start will changeTime,
//even number of start will not
always @(posedge start)
begin
  changeTime <= ~changeTime;
end

endmodule

final/watchController/WatchCtrl.v
`include "./StopWatch.v"
`include "./AlarmModule.v"
`include "./SevenSegDecoder.v"
`include "./Watch.v"
`include "./SetTime.v"
//TODO append modules

module WatchCtrl (
  input[2:0] mode,
  input resetTime, setValue, upTime, nextd,
  input clk, start_resume, stop,
  
  //output to sevensegdecoder
  output[6:0] d3, d2, d1, d0, 

  output alarmBeep
);

//VARIABLE DECLARTION
//constants for mode
parameter WATCH = 3'b000,
  STOPWATCH = 3'b001
  ;

//For display
reg [3:0] dis3, dis2, dis1, dis0; 

//internal value of SetTime
wire [3:0] St_hour1, St_hour0, St_min1, St_min0;
//internal value of Watch
wire [3:0] W_hour1, W_hour0, W_min1, W_min0;
//internal value of stopwatch
reg [3:0] Sw_min, Sw_sec1, Sw_sec0, Sw_milSec;
//internal value of Alarm
reg [3:0] Alm_hour1, Alm_hour0, Alm_min1, Alm_min0;
//internal value of Day
reg [3:0] Day_3, Day_2,Day_1,Day_0;

//ENDOF VARIABLE DECLARTIONS

//MODOLE DECLATIONS

//input
SetTime timeset(
  St_hour1,St_hour0,St_min1,St_min0,
  setValue,resetTime,nextd,upTime
);

//internal module
AlarmModule alm(
  alarmBeep,
  //internal var
  Alm_hour1, Alm_hour0, Alm_min1, Alm_min0,
  setValue,resetTime,clk
);
StopWatch stopwatch();

Watch watch(
  W_hour1, W_hour0, W_min1, W_min0,
  start_resume,resetTime,stop,clk,setValue
);


//display
SevenSegDecoder first(
  dis3,d3[0],d3[1],d3[2],d3[3],d3[4],d3[5],d3[6]
);
SevenSegDecoder second(
  dis2,d2[0],d2[1],d2[2],d2[3],d2[4],d2[5],d2[6]
);
SevenSegDecoder third(
  dis1,d1[0],d1[1],d1[2],d1[3],d1[4],d1[5],d1[6]
);
SevenSegDecoder fourth(
  dis0,d0[0],d0[1],d0[2],d0[3],d0[4],d0[5],d0[6]
);

//END OF MODULE DECLATIONS

//BEHAVIOR
always @(posedge clk)
begin
  //setValue overrides display, changing curr mode's value
  if  (setValue == 1)
  begin
    if (mode == WATCH)
    begin
      dis3 <= St_hour1;
      dis2 <= St_hour0;
      dis1 <= St_min1;
      dis0 <= St_min0;
      //after this, give input to clock
    end
    if (mode == STOPWATCH)
    begin
    end
  end
  
  //base mod: watch
  else if (mode == WATCH)
  begin
      dis3 <= W_hour1;
      dis2 <= W_hour0;
      dis1 <= W_min1;
      dis0 <= W_min0;
  end

  //stopwatch
  else if (mode == STOPWATCH) 
  begin
      dis3 <= 3'b000;
      dis2 <= 3'b000;
      dis1 <= 3'b000;
      dis0 <= 3'b000;
  end
  
end
//ENDOFBEHAVIOR

  
endmodule

final/watchController/WatchCtrl_test.v
`include "./WatchCtrl.v"

module WatchCtrl_test;

reg [2:0]mode; //selection of output mode

reg resetTime, setValue, upTime, nextDigit; //change time value for alarm and watch
reg clk, stop;
reg start_resume;

wire[6:0] digit3, digit2, digit1, digit0; //SevenSegDecoder
wire alarmBeep;

WatchCtrl uut(
  mode,
  resetTime, setValue, upTime, nextDigit, 
  clk, start_resume, stop, 
  digit3, digit2, digit1, digit0, 
  alarmBeep
);

initial begin
  resetTime = 1;
  clk = 0;
  upTime = 0;
  setValue = 0;
  mode = 0;
  $dumpfile("wave.vcd");
  $dumpvars(0,WatchCtrl_test);
  forever begin
    #1 clk = ~clk;
  end 
end 

initial begin
  #100
  begin
    resetTime <= 0;
    start_resume <= 1;
  end
  #10 mode = 3'b011;
  #100 setValue = 1;
    #10 upTime = 1;
    #10 upTime = 0;
    #10 upTime = 1;
    #10 upTime = 0;
    #10 upTime = 1;
    #10 upTime = 0;
    #10 upTime = 1;
    #10 upTime = 0;
    #10 upTime = 1;
    #10 upTime = 0;
    #10 upTime = 1;
    #10 upTime = 0;
    #10 upTime = 1;
    #10 upTime = 0;
  #10 setValue = 0;
    
  mode = 3'b001;
  #200
  mode = 3'b000;

  #1000 $finish;
end 
endmodule

final/watchController/wave.vcd
$date
	Sat Jun 13 18:43:59 2015
$end
$version
	Icarus Verilog
$end
$timescale
	1s
$end
$scope module WatchCtrl_test $end
$var wire 1 ! alarmBeep $end
$var wire 7 " digit0 [6:0] $end
$var wire 7 # digit1 [6:0] $end
$var wire 7 $ digit2 [6:0] $end
$var wire 7 % digit3 [6:0] $end
$var reg 1 & clk $end
$var reg 3 ' mode [2:0] $end
$var reg 1 ( nextDigit $end
$var reg 1 ) resetTime $end
$var reg 1 * setValue $end
$var reg 1 + start_resume $end
$var reg 1 , stop $end
$var reg 1 - upTime $end
$scope module uut $end
$var wire 4 . St_hour0 [3:0] $end
$var wire 4 / St_hour1 [3:0] $end
$var wire 4 0 St_min0 [3:0] $end
$var wire 4 1 St_min1 [3:0] $end
$var wire 4 2 W_hour0 [3:0] $end
$var wire 4 3 W_hour1 [3:0] $end
$var wire 4 4 W_min0 [3:0] $end
$var wire 4 5 W_min1 [3:0] $end
$var wire 1 ! alarmBeep $end
$var wire 1 6 clk $end
$var wire 7 7 d0 [6:0] $end
$var wire 7 8 d1 [6:0] $end
$var wire 7 9 d2 [6:0] $end
$var wire 7 : d3 [6:0] $end
$var wire 3 ; mode [2:0] $end
$var wire 1 < nextd $end
$var wire 1 = resetTime $end
$var wire 1 > setValue $end
$var wire 1 ? start_resume $end
$var wire 1 @ stop $end
$var wire 1 A upTime $end
$var reg 4 B Alm_hour0 [3:0] $end
$var reg 4 C Alm_hour1 [3:0] $end
$var reg 4 D Alm_min0 [3:0] $end
$var reg 4 E Alm_min1 [3:0] $end
$var reg 4 F dis0 [3:0] $end
$var reg 4 G dis1 [3:0] $end
$var reg 4 H dis2 [3:0] $end
$var reg 4 I dis3 [3:0] $end
$scope module timeset $end
$var wire 1 < nextDigit $end
$var wire 1 = reset $end
$var wire 1 > start $end
$var wire 1 A up $end
$var reg 1 J changeTime $end
$var reg 2 K currNum [1:0] $end
$var reg 4 L h0 [3:0] $end
$var reg 4 M h1 [3:0] $end
$var reg 4 N m0 [3:0] $end
$var reg 4 O m1 [3:0] $end
$upscope $end
$scope module alm $end
$var wire 1 = alarmReset $end
$var wire 1 > alarmSet $end
$var wire 1 6 clk $end
$var wire 4 P curHour0 [3:0] $end
$var wire 4 Q curHour1 [3:0] $end
$var wire 4 R curMin0 [3:0] $end
$var wire 4 S curMin1 [3:0] $end
$var reg 1 T alarm $end
$var reg 4 U savHour0 [3:0] $end
$var reg 4 V savHour1 [3:0] $end
$var reg 4 W savMin0 [3:0] $end
$var reg 4 X savMin1 [3:0] $end
$upscope $end
$scope module stopwatch $end
$var wire 1 Y clk $end
$var wire 4 Z milSec0 [3:0] $end
$var wire 4 [ min0 [3:0] $end
$var wire 1 \ min0clk $end
$var wire 1 ] reset $end
$var wire 4 ^ sec0 [3:0] $end
$var wire 1 _ sec0clk $end
$var wire 4 ` sec1 [3:0] $end
$var wire 1 a sec1clk $end
$var wire 1 b start_resume $end
$var wire 1 c stop $end
$scope module MIL0 $end
$var wire 1 Y clk $end
$var wire 1 ] reset $end
$var wire 1 b start_resume $end
$var wire 1 c stop $end
$var reg 1 d cout $end
$var reg 4 e current [3:0] $end
$var reg 4 f next [3:0] $end
$var reg 4 g number [3:0] $end
$upscope $end
$scope module SEC0 $end
$var wire 1 _ clk $end
$var wire 1 ] reset $end
$var wire 1 b start_resume $end
$var wire 1 c stop $end
$var reg 1 h cout $end
$var reg 4 i current [3:0] $end
$var reg 4 j next [3:0] $end
$var reg 4 k number [3:0] $end
$upscope $end
$scope module SEC1 $end
$var wire 1 a clk $end
$var wire 1 ] reset $end
$var wire 1 b start_resume $end
$var wire 1 c stop $end
$var reg 1 l cout $end
$var reg 4 m current [3:0] $end
$var reg 4 n next [3:0] $end
$var reg 4 o number [3:0] $end
$upscope $end
$scope module MIN0 $end
$var wire 1 \ clk $end
$var wire 1 ] reset $end
$var wire 1 b start_resume $end
$var wire 1 c stop $end
$var reg 1 p cout $end
$var reg 4 q current [3:0] $end
$var reg 4 r next [3:0] $end
$var reg 4 s number [3:0] $end
$upscope $end
$upscope $end
$scope module watch $end
$var wire 1 6 clk $end
$var wire 1 t h0clk $end
$var wire 1 u h1clk $end
$var wire 4 v hr0 [3:0] $end
$var wire 4 w hr1 [3:0] $end
$var wire 4 x min0 [3:0] $end
$var wire 4 y min1 [3:0] $end
$var wire 1 z min1clk $end
$var wire 1 = reset $end
$var wire 1 > setTime $end
$var wire 1 ? start_resume $end
$var wire 1 @ stop $end
$scope module Min0 $end
$var wire 1 6 clk $end
$var wire 1 = reset $end
$var wire 1 ? start_resume $end
$var wire 1 @ stop $end
$var reg 1 { cout $end
$var reg 4 | current [3:0] $end
$var reg 4 } next [3:0] $end
$var reg 4 ~ number [3:0] $end
$upscope $end
$scope module Min1 $end
$var wire 1 z clk $end
$var wire 1 = reset $end
$var wire 1 ? start_resume $end
$var wire 1 @ stop $end
$var reg 1 !" cout $end
$var reg 4 "" current [3:0] $end
$var reg 4 #" next [3:0] $end
$var reg 4 $" number [3:0] $end
$upscope $end
$scope module Hr0 $end
$var wire 1 t clk $end
$var wire 1 = reset $end
$var wire 1 ? start_resume $end
$var wire 1 @ stop $end
$var reg 1 %" cout $end
$var reg 4 &" current [3:0] $end
$var reg 4 '" next [3:0] $end
$var reg 4 (" number [3:0] $end
$upscope $end
$scope module Hr1 $end
$var wire 1 u clk $end
$var wire 1 = reset $end
$var wire 1 ? start_resume $end
$var wire 1 @ stop $end
$var reg 1 )" cout $end
$var reg 4 *" current [3:0] $end
$var reg 4 +" next [3:0] $end
$var reg 4 ," number [3:0] $end
$upscope $end
$upscope $end
$scope module first $end
$var wire 4 -" number [3:0] $end
$var reg 1 ." A $end
$var reg 1 /" B $end
$var reg 1 0" C $end
$var reg 1 1" D $end
$var reg 1 2" E $end
$var reg 1 3" F $end
$var reg 1 4" G $end
$upscope $end
$scope module second $end
$var wire 4 5" number [3:0] $end
$var reg 1 6" A $end
$var reg 1 7" B $end
$var reg 1 8" C $end
$var reg 1 9" D $end
$var reg 1 :" E $end
$var reg 1 ;" F $end
$var reg 1 <" G $end
$upscope $end
$scope module third $end
$var wire 4 =" number [3:0] $end
$var reg 1 >" A $end
$var reg 1 ?" B $end
$var reg 1 @" C $end
$var reg 1 A" D $end
$var reg 1 B" E $end
$var reg 1 C" F $end
$var reg 1 D" G $end
$upscope $end
$scope module fourth $end
$var wire 4 E" number [3:0] $end
$var reg 1 F" A $end
$var reg 1 G" B $end
$var reg 1 H" C $end
$var reg 1 I" D $end
$var reg 1 J" E $end
$var reg 1 K" F $end
$var reg 1 L" G $end
$upscope $end
$upscope $end
$upscope $end
$enddefinitions $end
#0
$dumpvars
xL"
xK"
xJ"
xI"
xH"
xG"
xF"
bx E"
xD"
xC"
xB"
xA"
x@"
x?"
x>"
bx ="
x<"
x;"
x:"
x9"
x8"
x7"
x6"
bx 5"
x4"
x3"
x2"
x1"
x0"
x/"
x."
bx -"
bx ,"
b0 +"
bx *"
0)"
bx ("
b0 '"
bx &"
0%"
bx $"
b0 #"
bx ""
0!"
bx ~
b0 }
bx |
0{
0z
bx y
bx x
bx w
bx v
0u
0t
bx s
bx r
bx q
xp
bx o
bx n
bx m
xl
bx k
bx j
bx i
xh
bx g
bx f
bx e
xd
zc
zb
xa
bx `
x_
bx ^
z]
x\
bx [
bx Z
zY
bx X
bx W
bx V
bx U
xT
bx S
bx R
bx Q
bx P
b0 O
b0 N
b0 M
b0 L
b0 K
0J
bx I
bx H
bx G
bx F
bx E
bx D
bx C
bx B
0A
x@
x?
0>
1=
x<
b0 ;
bx :
bx 9
bx 8
bx 7
06
bx 5
bx 4
bx 3
bx 2
b0 1
b0 0
b0 /
b0 .
0-
x,
x+
0*
1)
x(
b0 '
0&
bx %
bx $
bx #
bx "
x!
$end
#1
b0 ~
b0 4
b0 x
b0 V
b0 U
b0 X
b0 W
b0 |
1&
16
#2
0&
06
#3
0L"
1K"
1J"
1I"
1H"
1G"
1F"
b111111 "
b111111 7
b0 F
b0 E"
1&
16
#4
0&
06
#5
1&
16
#6
0&
06
#7
1&
16
#8
0&
06
#9
1&
16
#10
0&
06
#11
1&
16
#12
0&
06
#13
1&
16
#14
0&
06
#15
1&
16
#16
0&
06
#17
1&
16
#18
0&
06
#19
1&
16
#20
0&
06
#21
1&
16
#22
0&
06
#23
1&
16
#24
0&
06
#25
1&
16
#26
0&
06
#27
1&
16
#28
0&
06
#29
1&
16
#30
0&
06
#31
1&
16
#32
0&
06
#33
1&
16
#34
0&
06
#35
1&
16
#36
0&
06
#37
1&
16
#38
0&
06
#39
1&
16
#40
0&
06
#41
1&
16
#42
0&
06
#43
1&
16
#44
0&
06
#45
1&
16
#46
0&
06
#47
1&
16
#48
0&
06
#49
1&
16
#50
0&
06
#51
1&
16
#52
0&
06
#53
1&
16
#54
0&
06
#55
1&
16
#56
0&
06
#57
1&
16
#58
0&
06
#59
1&
16
#60
0&
06
#61
1&
16
#62
0&
06
#63
1&
16
#64
0&
06
#65
1&
16
#66
0&
06
#67
1&
16
#68
0&
06
#69
1&
16
#70
0&
06
#71
1&
16
#72
0&
06
#73
1&
16
#74
0&
06
#75
1&
16
#76
0&
06
#77
1&
16
#78
0&
06
#79
1&
16
#80
0&
06
#81
1&
16
#82
0&
06
#83
1&
16
#84
0&
06
#85
1&
16
#86
0&
06
#87
1&
16
#88
0&
06
#89
1&
16
#90
0&
06
#91
1&
16
#92
0&
06
#93
1&
16
#94
0&
06
#95
1&
16
#96
0&
06
#97
1&
16
#98
0&
06
#99
1&
16
#100
b0 ,"
b0 3
b0 w
b1 +"
1)"
b0 *"
b0 ("
b0 2
b0 v
b1 '"
1%"
1u
b0 &"
b0 $"
b0 5
b0 y
b1 #"
1!"
1t
b0 ""
b1 }
1{
1z
1+
1?
0)
0=
0&
06
#101
b1 ~
b1 4
b1 x
b10 }
0{
0z
0D"
1C"
1B"
1A"
1@"
1?"
1>"
b111111 #
b111111 8
0<"
1;"
1:"
19"
18"
17"
16"
b111111 $
b111111 9
04"
13"
12"
11"
10"
1/"
1."
b111111 %
b111111 :
b1 |
b0 G
b0 ="
b0 H
b0 5"
b0 I
b0 -"
1&
16
#102
0&
06
#103
0K"
0J"
0I"
0F"
b110 "
b110 7
b10 ~
b10 4
b10 x
b11 }
b1 F
b1 E"
b10 |
1&
16
#104
0&
06
#105
b11 ~
b11 4
b11 x
b100 }
1L"
1J"
1I"
0H"
1F"
b1011011 "
b1011011 7
b11 |
b10 F
b10 E"
1&
16
#106
0&
06
#107
0J"
1H"
b1001111 "
b1001111 7
b100 ~
b100 4
b100 x
b101 }
b11 F
b11 E"
b100 |
1&
16
#108
0&
06
#109
b101 ~
b101 4
b101 x
b110 }
1K"
0I"
0F"
b1100110 "
b1100110 7
b101 |
b100 F
b100 E"
1&
16
#110
0&
06
#111
1I"
0G"
1F"
b1101101 "
b1101101 7
b110 ~
b110 4
b110 x
b111 }
b101 F
b101 E"
b110 |
1&
16
#112
0&
06
#113
b111 ~
b111 4
b111 x
b1000 }
1J"
b1111101 "
b1111101 7
b111 |
b110 F
b110 E"
1&
16
#114
0&
06
#115
0L"
0J"
0I"
1G"
b100111 "
b100111 7
b1000 ~
b1000 4
b1000 x
b1001 }
b111 F
b111 E"
b1000 |
1&
16
#116
0&
06
#117
b1001 ~
b1001 4
b1001 x
b0 }
1L"
1J"
1I"
b1111111 "
b1111111 7
b1001 |
b1000 F
b1000 E"
1&
16
#118
0&
06
#119
b1 $"
b1 5
b1 y
b10 #"
0!"
0t
b1 ""
0L"
0J"
b101111 "
b101111 7
b0 ~
b0 4
b0 x
b1 }
1{
1z
b1001 F
b1001 E"
b0 |
1&
16
#120
0&
06
#121
b1 ~
b1 4
b1 x
b10 }
0{
0z
1J"
b111111 "
b111111 7
0C"
0B"
0A"
0>"
b110 #
b110 8
b1 |
b0 F
b0 E"
b1 G
b1 ="
1&
16
#122
0&
06
#123
0K"
0J"
0I"
0F"
b110 "
b110 7
b10 ~
b10 4
b10 x
b11 }
b1 F
b1 E"
b10 |
1&
16
#124
0&
06
#125
b11 ~
b11 4
b11 x
b100 }
1L"
1J"
1I"
0H"
1F"
b1011011 "
b1011011 7
b11 |
b10 F
b10 E"
1&
16
#126
0&
06
#127
0J"
1H"
b1001111 "
b1001111 7
b100 ~
b100 4
b100 x
b101 }
b11 F
b11 E"
b100 |
1&
16
#128
0&
06
#129
b101 ~
b101 4
b101 x
b110 }
1K"
0I"
0F"
b1100110 "
b1100110 7
b101 |
b100 F
b100 E"
1&
16
#130
0&
06
#131
1I"
0G"
1F"
b1101101 "
b1101101 7
b110 ~
b110 4
b110 x
b111 }
b101 F
b101 E"
b110 |
1&
16
#132
0&
06
#133
b111 ~
b111 4
b111 x
b1000 }
1J"
b1111101 "
b1111101 7
b111 |
b110 F
b110 E"
1&
16
#134
0&
06
#135
0L"
0J"
0I"
1G"
b100111 "
b100111 7
b1000 ~
b1000 4
b1000 x
b1001 }
b111 F
b111 E"
b1000 |
1&
16
#136
0&
06
#137
b1001 ~
b1001 4
b1001 x
b0 }
1L"
1J"
1I"
b1111111 "
b1111111 7
b1001 |
b1000 F
b1000 E"
1&
16
#138
0&
06
#139
b10 $"
b10 5
b10 y
b11 #"
b10 ""
0L"
0J"
b101111 "
b101111 7
b0 ~
b0 4
b0 x
b1 }
1{
1z
b1001 F
b1001 E"
b0 |
1&
16
#140
0&
06
#141
b1 ~
b1 4
b1 x
b10 }
0{
0z
1J"
b111111 "
b111111 7
1D"
1B"
1A"
0@"
1>"
b1011011 #
b1011011 8
b1 |
b0 F
b0 E"
b10 G
b10 ="
1&
16
#142
0&
06
#143
0K"
0J"
0I"
0F"
b110 "
b110 7
b10 ~
b10 4
b10 x
b11 }
b1 F
b1 E"
b10 |
1&
16
#144
0&
06
#145
b11 ~
b11 4
b11 x
b100 }
1L"
1J"
1I"
0H"
1F"
b1011011 "
b1011011 7
b11 |
b10 F
b10 E"
1&
16
#146
0&
06
#147
0J"
1H"
b1001111 "
b1001111 7
b100 ~
b100 4
b100 x
b101 }
b11 F
b11 E"
b100 |
1&
16
#148
0&
06
#149
b101 ~
b101 4
b101 x
b110 }
1K"
0I"
0F"
b1100110 "
b1100110 7
b101 |
b100 F
b100 E"
1&
16
#150
0&
06
#151
1I"
0G"
1F"
b1101101 "
b1101101 7
b110 ~
b110 4
b110 x
b111 }
b101 F
b101 E"
b110 |
1&
16
#152
0&
06
#153
b111 ~
b111 4
b111 x
b1000 }
1J"
b1111101 "
b1111101 7
b111 |
b110 F
b110 E"
1&
16
#154
0&
06
#155
0L"
0J"
0I"
1G"
b100111 "
b100111 7
b1000 ~
b1000 4
b1000 x
b1001 }
b111 F
b111 E"
b1000 |
1&
16
#156
0&
06
#157
b1001 ~
b1001 4
b1001 x
b0 }
1L"
1J"
1I"
b1111111 "
b1111111 7
b1001 |
b1000 F
b1000 E"
1&
16
#158
0&
06
#159
b11 $"
b11 5
b11 y
b100 #"
b11 ""
0L"
0J"
b101111 "
b101111 7
b0 ~
b0 4
b0 x
b1 }
1{
1z
b1001 F
b1001 E"
b0 |
1&
16
#160
0&
06
#161
b1 ~
b1 4
b1 x
b10 }
0{
0z
1J"
b111111 "
b111111 7
0B"
1@"
b1001111 #
b1001111 8
b1 |
b0 F
b0 E"
b11 G
b11 ="
1&
16
#162
0&
06
#163
0K"
0J"
0I"
0F"
b110 "
b110 7
b10 ~
b10 4
b10 x
b11 }
b1 F
b1 E"
b10 |
1&
16
#164
0&
06
#165
b11 ~
b11 4
b11 x
b100 }
1L"
1J"
1I"
0H"
1F"
b1011011 "
b1011011 7
b11 |
b10 F
b10 E"
1&
16
#166
0&
06
#167
0J"
1H"
b1001111 "
b1001111 7
b100 ~
b100 4
b100 x
b101 }
b11 F
b11 E"
b100 |
1&
16
#168
0&
06
#169
b101 ~
b101 4
b101 x
b110 }
1K"
0I"
0F"
b1100110 "
b1100110 7
b101 |
b100 F
b100 E"
1&
16
#170
0&
06
#171
1I"
0G"
1F"
b1101101 "
b1101101 7
b110 ~
b110 4
b110 x
b111 }
b101 F
b101 E"
b110 |
1&
16
#172
0&
06
