final/watchController/SevenSegDecoder.v
module SevenSegDecoder(
  input[3:0] number,
  output A, B, C, D, E, F, G
);

reg A,B,C,D,E,F,G;

//fix this to only combinational logic?
always @(number)
begin
  if  (number == 4'b0000)
  begin
    A = 1;
    B = 1;
    C = 1;
    D = 1;
    E = 1;
    F = 1;
    G = 0;
  end
  else if  (number == 4'b0001)
  begin
    A = 0;
    B = 1;
    C = 1;
    D = 0;
    E = 0;
    F = 0;
    G = 0;
  end
  else if  (number == 4'b0010)
  begin
    A = 1;
    B = 1;
    C = 0;
    D = 1;
    E = 1;
    F = 0;
    G = 1;
  end
  else if  (number == 4'b0011)
  begin
    A = 1;
    B = 1;
    C = 1;
    D = 1;
    E = 0;
    F = 0;
    G = 1;
  end
  else if  (number == 4'b0100)
  begin
    A = 0;
    B = 1;
    C = 1;
    D = 0;
    E = 0;
    F = 1;
    G = 1;
  end
  else if  (number == 4'b0101)
  begin
    A = 1;
    B = 0;
    C = 1;
    D = 1;
    E = 0;
    F = 1;
    G = 1;
  end
  else if  (number == 4'b0110)
  begin
    A = 1;
    B = 0;
    C = 1;
    D = 1;
    E = 1;
    F = 1;
    G = 1;
  end
  else if  (number == 4'b0111)
  begin
    A = 1;
    B = 1;
    C = 1;
    D = 0;
    E = 0;
    F = 1;
    G = 0;
  end
  else if  (number == 4'b1000)
  begin
    A = 1;
    B = 1;
    C = 1;
    D = 1;
    E = 1;
    F = 1;
    G = 1;
  end
  else if  (number == 4'b1001)
  begin
    A = 1;
    B = 1;
    C = 1;
    D = 1;
    E = 0;
    F = 1;
    G = 1;
  end
end 
endmodule

final/watchController/Mod2Counter.v
`ifndef MOD2_V
`define MOD2_V
module Mod2Counter(
  output reg[3:0] number,
  output reg cout,
  input start_resume,reset, stop, clk
);

reg [3:0] current, next;

parameter zero =4'b0000,
  one=4'b0001;
  //two=4'b0010,

always @(current or start_resume or reset or stop) 
begin
  if(start_resume==1 && current != one)
  begin
    if  (current == zero)
    begin
      cout = 1;
    end
    else
    begin
      cout = 0;
    end
    next=current + 1;
    number=current;
  end
  else if(start_resume==0)
  begin
    cout = 0;
    next=current;
    number=current;
  end
  else if(stop==1)
  begin
    cout = 0;
    next=current;
    number=current;
  end
  else if(reset==1) 
  begin
    cout = 0;
    next=zero;
    number=current;
  end

  //change this to for counter of different modulo
  if(current == one)
  begin
    next = zero;
    cout = 0;
    number = current;
  end

end

always @(posedge clk)
begin
  begin
    if(reset==1)
      current <= zero;
    else
      current <= next;
  end
end
endmodule
`endif

final/watchController/Mod13Counter.v
`ifndef MOD13_V
`define MOD13_V
//since modulo is expensive(is it?)
//do it manually
//first digit of hour display
//should have 24/12 mode input?????
module Mod13Counter(
  output reg[3:0] number,
  output reg cout,
  input start_resume,reset, stop, clk
);

reg [3:0] current, next;

parameter zero =4'b0000,
  one=4'b0001,
  two=4'b0010,
  three=4'b0011,
  four=4'b0100,
  five=4'b0101,
  six=4'b0110,
  seven=4'b0111,
  eight=4'b1000,
  nine=4'b1001,
  ten=4'b1010,
  eleven = 4'b1011,
  twelve = 4'b1100;
  

always @(current or start_resume or reset or stop) 
begin
  if(start_resume==1 && current != twelve)
  begin
    if  (current == zero)
    begin
      cout = 1;
    end
    else
    begin
      cout = 0;
    end
    next=current + 1;
	if(current == ten)
		number = zero;
	else if(current == eleven)
		number = one;
	else if(current == twelve)
		number = two;
	else
		number = current;
  end
  else if(start_resume==0)
  begin
    cout = 0;
    next=current;
    if(current == ten)
		number = zero;
	else if(current == eleven)
		number = one;
	else if(current == twelve)
		number = two;
	else
		number = current;
  end
  else if(stop==1)
  begin
    cout = 0;
    next=current;
    if(current == ten)
		number = zero;
	else if(current == eleven)
		number = one;
	else if(current == twelve)
		number = two;
	else
		number = current;
  end
  else if(reset==1) 
  begin
    cout = 0;
    next=zero;
    if(current == ten)
		number = zero;
	else if(current == eleven)
		number = one;
	else if(current == twelve)
		number = two;
	else
		number = current;
  end

  //change this to for counter of different modulo
  if(current == twelve)
  begin
    next = zero;
    cout = 0;
    if(current == ten)
		number = zero;
	else if(current == eleven)
		number = one;
	else if(current == twelve)
		number = two;
	else
		number = current;
  end

end

always @(posedge clk)
begin
  begin
    if(reset==1)
      current <= zero;
    else
      current <= next;
  end
end
endmodule
`endif

final/watchController/Mod6Counter.v
`ifndef MOD6_V
`define MOD6_V
module Mod6Counter(
  output reg[3:0] number,
  output reg cout,
  input start_resume,reset, stop, clk
);

reg [3:0] current, next;

parameter zero =4'b0000,
  one=4'b0001,
  two=4'b0010,
  three=4'b0011,
  four=4'b0100,
  five=4'b0101,
  six=4'b0110,
  seven=4'b0111,
  eight=4'b1000,
  nine=4'b1001;

always @(current or start_resume or reset or stop) 
begin
  if(start_resume==1 && current != nine)
  begin
    if  (current == zero)
    begin
      cout = 1;
    end
    else
    begin
      cout = 0;
    end
    next=current + 1;
    number=current;
  end
  else if(start_resume==0)
  begin
    cout = 0;
    next=current;
    number=current;
  end
  else if(stop==1)
  begin
    cout = 0;
    next=current;
    number=current;
  end
  else if(reset==1) 
  begin
    cout = 0;
    next=zero;
    number=current;
  end

  //change this to for counter of different modulo
  if(current == five)
  begin
    next = zero;
    cout = 0;
    number = current;
  end

end

always @(posedge clk)
begin
  begin
    if(reset==1)
      current <= zero;
    else
      current <= next;
  end
end
endmodule
`endif

final/watchController/Mod10Counter.v
`ifndef MOD10_V
`define MOD10_V
module Mod10Counter(
  output[3:0] number,
  output cout,
  input start_resume,reset, stop, clk
);

reg [3:0] current, next;
reg [3:0] number;
reg cout;

parameter zero =4'b0000,
  one=4'b0001,
  two=4'b0010,
  three=4'b0011,
  four=4'b0100,
  five=4'b0101,
  six=4'b0110,
  seven=4'b0111,
  eight=4'b1000,
  nine=4'b1001;

always @(current or start_resume or reset or stop) 
begin
  if(start_resume==1 && current != nine)
  begin
    if  (current == zero)
    begin
      cout = 1;
    end
    else
    begin
      cout = 0;
    end
    next=current + 1;
    number=current;
  end
  else if(start_resume==0)
  begin
    cout = 0;
    next=current;
    number=current;
  end
  else if(stop==1)
  begin
    cout = 0;
    next=current;
    number=current;
  end
  else if(reset==1) 
  begin
    cout = 0;
    next=zero;
    number=current;
  end

  //change this to for counter of different modulo
  if(current == nine)
  begin
    next = zero;
    cout = 0;
    number = current;
  end

end

always @(posedge clk)
begin
  begin
    if(reset==1)
      current <= zero;
    else
      current <= next;
  end
end
endmodule
`endif

final/watchController/Watch.v
`include "./Mod6Counter.v"
`include "./Mod10Counter.v"
`include "./Mod2Counter.v"//hour 1 digit
`include "./Mod13Counter.v" //hour 0 digit

//able to set time 
module Watch (
  output[3:0] hr1, hr0, min1, min0,
  input start_resume,reset, stop, clk, setTime
);

wire  hr1, hr0, min1, min0;
wire min1clk, h0clk, h1clk;

Mod10Counter Min0(min0,min1clk,start_resume,reset,stop,clk);
Mod6Counter Min1(min1,h0clk,start_resume,reset,stop,min1clk);
Mod13Counter Hr0(hr0,h1clk,start_resume,reset,stop,h0clk);
Mod2Counter Hr1(hr1,,start_resume,reset,stop,h1clk);
  
endmodule

final/watchController/StopWatch.v
`include "./Counter/Mod6Counter.v"
`include "./Counter/Mod10Counter.v"



module StopWatch(
  output[3:0] min0, sec1, sec0, milSec0,
  input start_resume,reset, stop, clk
);
wire min0,sec1,sec0,milSec0;

wire min0clk, sec1clk, sec0clk;


//devide the clk and put it as input.
Mod10Counter MIL0(milSec0, sec0clk, start_resume,reset,stop,clk);
Mod10Counter SEC0(sec0, sec1clk, start_resume,reset,stop,sec0clk);
Mod6Counter SEC1(sec1, min0clk, start_resume,reset,stop,sec1clk);
Mod10Counter MIN0(min0,,start_resume,reset,stop,min0clk);

endmodule

final/watchController/AlarmModule.v
//TODO get input from SetTime
module AlarmModule (
  output alarm,
  output[3:0] disH1,disH0,disM1,disM0,
  input[3:0] curHour1, curHour0, curMin1, curMin0, //read time every n's clk
  input alarmSet, alarmReset, clk
);
reg alarm;
reg disH1,disH0,disM1,disM0;
reg[3:0] savMin0, savMin1, savHour0, savHour1; //save alarm time

//if curMin0 changes, everything changes
always @(curMin0)
begin
  if  (
    savMin0 == curMin0   &&
    savMin1 == curMin1   &&
    savHour0 == curHour0 &&
    savHour1 == curHour1 &&
    alarmSet != 1
  ) 
  begin
    alarm = 1;
  end
  else 
  begin
    alarm = 0;
  end 
end

always @(posedge clk)
begin
  begin
    if(alarmReset==1)
    begin
      savMin0 <= 0;
      savMin1 <= 0;
      savHour0 <= 0;
      savHour1 <= 0;
    end 
    else if(alarmSet == 1)
    begin
      savMin0 <= curMin0;
      savMin1 <= curMin1;
      savHour0 <= curHour0;
      savHour1 <= curHour1;
    end 
    else 
    begin
      disM0<=savMin0;
      disM1<=savMin1;
      disH0<=savHour0;
      disH1<=savHour1;
    end
  end
end


endmodule

final/settime/SetTime.v
//based on mode, should use diffrent modulous for time???
//NO! Alarm and clock use the same time scale.
//How should we return output?
module SetTime (
  output[3:0] h1, h0, m1, m0,
  input start, reset, nextDigit, up
);

reg h1, h0, m1, m0;
//wire current, next;
reg[1:0] currNum;
reg changeTime;

always @(posedge up or posedge reset)
begin
  begin
    if  (reset == 1)
    begin
      currNum <= 0;
      changeTime <= 0;
      h1 <= 0;
      h0 <= 0;
      m1 <= 0;
      m0 <= 0;
    end
    else if  (currNum == 3 && changeTime==1)
      h1 <= (h1 + 1)%2; //TODO should change this depending on time mode
    else if  (currNum == 2&& changeTime==1)
      h0 <= (h0 + 1)%10; //can use 10 modulous instead of 12 because there is not cout
    else if  (currNum == 1&& changeTime==1)
      m1 <= (m1 + 1)%6;
    else if  (currNum == 0&& changeTime==1)
      m0 <= (m0 + 1)%10;
  end
end

always @(posedge nextDigit)
begin
  begin
    if  (currNum == 3)
      currNum <= 0;
    else
      currNum <= currNum + 1;
  end
end

//odd number of start will changeTime,
//even number of start will not
always @(posedge start)
begin
  changeTime <= ~changeTime;
end

endmodule

final/watchController/WatchCtrl.v
`include "./StopWatch.v"
`include "./AlarmModule.v"
`include "./SevenSegDecoder.v"
`include "./Watch.v"
`include "./SetTime.v"

module WatchCtrl (
  input[2:0] mode,
  input resetTime, setValue, upTime, nextd,
  input clk, start_resume, stop,
  
  //output to sevensegdecoder
  output[6:0] d3, d2, d1, d0, 

  output alarmBeep
);

//VARIABLE DECLARTION
//TODO constants for mode
parameter WATCH = 3'b000,
  STOPWATCH = 3'b001,
  ALARM = 3'b010,
  DAY = 3'b011
  ;

//For display
reg [3:0] dis3, dis2, dis1, dis0; 

//internal value of SetTime
wire [3:0] St_hour1, St_hour0, St_min1, St_min0;
//internal value of Watch
wire [3:0] W_hour1, W_hour0, W_min1, W_min0;
//internal value of stopwatch
reg [3:0] Sw_min, Sw_sec1, Sw_sec0, Sw_milSec;
//internal value of Alarm
reg [3:0] Alm_hour1, Alm_hour0, Alm_min1, Alm_min0;
//ouput value of Alarm
wire [3:0] Alm_hour1_d, Alm_hour0_d, Alm_min1_d, Alm_min0_d;
//internal value of Day
reg [3:0] Day_3, Day_2,Day_1,Day_0;
//internal value for setbutton
reg set;

//ENDOF VARIABLE DECLARTIONS

//MODULE DECLATIONS
//TODO append modules

//input
SetTime timeset(
  St_hour1,St_hour0,St_min1,St_min0,
  setValue,resetTime,nextd,upTime
);

//ALarm module should always run
AlarmModule alm(
  alarmBeep,
  //displays saved time
  Alm_hour1_d, Alm_hour0_d, Alm_min1_d, Alm_min0_d,
  
  //internal var
  Alm_hour1, Alm_hour0, Alm_min1, Alm_min0,
  setValue,resetTime,clk
);
StopWatch stopwatch();

Watch watch(
  W_hour1, W_hour0, W_min1, W_min0,
  start_resume,resetTime,stop,clk,setValue
);


//display
SevenSegDecoder first(
  dis3,d3[0],d3[1],d3[2],d3[3],d3[4],d3[5],d3[6]
);
SevenSegDecoder second(
  dis2,d2[0],d2[1],d2[2],d2[3],d2[4],d2[5],d2[6]
);
SevenSegDecoder third(
  dis1,d1[0],d1[1],d1[2],d1[3],d1[4],d1[5],d1[6]
);
SevenSegDecoder fourth(
  dis0,d0[0],d0[1],d0[2],d0[3],d0[4],d0[5],d0[6]
);

//END OF MODULE DECLATIONS

//BEHAVIOR
//FIXME if this chatters, only use clk
always @(posedge clk or mode) 
begin
  //setValue overrides display, changing curr mode's value
  if  (setValue == 1)
  begin
    if (mode == WATCH)
    begin
      dis3 <= St_hour1;
      dis2 <= St_hour0;
      dis1 <= St_min1;
      dis0 <= St_min0;
      //TODO after this, give input to clock
    end
    if (mode == ALARM)
    begin
      dis3 <= St_hour1;
      dis2 <= St_hour0;
      dis1 <= St_min1;
      dis0 <= St_min0;

      Alm_hour1 <= St_hour1; 
      Alm_hour0 <= St_hour0; 
      Alm_min1 <=St_min1; 
      Alm_min0 <= St_min0;
    end
    if (mode == DAY)
    begin

    end
  end
  
  //base mod: watch
  //FIXME fix this to switch case later
  else if (mode == WATCH)
  begin
      dis3 <= W_hour1;
      dis2 <= W_hour0;
      dis1 <= W_min1;
      dis0 <= W_min0;

      Alm_hour1 <= W_hour1; 
      Alm_hour0 <= W_hour0; 
      Alm_min1 <=  W_min1; 
      Alm_min0 <=  W_min0;
  end

  //stopwatch
  else if (mode == STOPWATCH) 
  begin
      dis3 <= 3'b000;
      dis2 <= 3'b000;
      dis1 <= 3'b000;
      dis0 <= 3'b000;

      Alm_hour1 <= W_hour1; 
      Alm_hour0 <= W_hour0; 
      Alm_min1 <=  W_min1; 
      Alm_min0 <=  W_min0;
  end
  
  //ALARM
  //FIXME displays saved time
  else if (mode == ALARM) 
  begin
      dis3 <= Alm_hour1_d;
      dis2 <= Alm_hour0_d;
      dis1 <= Alm_min1_d;
      dis0 <= Alm_min0_d;
  end
end
//ENDOFBEHAVIOR

  
endmodule

final/watchController/WatchCtrl_test.v
`include "./WatchCtrl.v"

module WatchCtrl_test;

reg [2:0]mode; //selection of output mode

reg resetTime, setValue, upTime, nextDigit; //change time value for alarm and watch
reg clk, stop;
reg start_resume;

wire[6:0] digit3, digit2, digit1, digit0; //SevenSegDecoder
wire alarmBeep;

WatchCtrl uut(
  mode,
  resetTime, setValue, upTime, nextDigit, 
  clk, start_resume, stop, 
  digit3, digit2, digit1, digit0, 
  alarmBeep
);

initial begin
  resetTime = 1;
  clk = 0;
  upTime = 0;
  setValue = 0;
  mode = 0;
  $dumpfile("wave.vcd");
  $dumpvars(0,WatchCtrl_test);
  forever begin
    #1 clk = ~clk;
  end 
end 

initial begin
  #100
  begin
    resetTime <= 0;
    start_resume <= 1;
  end
  #10 mode = 3'b011;
  #100 setValue = 1;
    #10 upTime = 1;
    #10 upTime = 0;
    #10 upTime = 1;
    #10 upTime = 0;
    #10 upTime = 1;
    #10 upTime = 0;
    #10 upTime = 1;
    #10 upTime = 0;
    #10 upTime = 1;
    #10 upTime = 0;
    #10 upTime = 1;
    #10 upTime = 0;
    #10 upTime = 1;
    #10 upTime = 0;
  #10 setValue = 0;
    
  mode = 3'b001;
  #200
  mode = 3'b000;

  #1000 $finish;
end 
endmodule

final/watchController/wave.vcd
$date
	Sat Jun 13 20:49:34 2015
$end
$version
	Icarus Verilog
$end
$timescale
	1s
$end
$scope module WatchCtrl_test $end
$var wire 1 ! alarmBeep $end
$var wire 7 " digit0 [6:0] $end
$var wire 7 # digit1 [6:0] $end
$var wire 7 $ digit2 [6:0] $end
$var wire 7 % digit3 [6:0] $end
$var reg 1 & clk $end
$var reg 3 ' mode [2:0] $end
$var reg 1 ( nextDigit $end
$var reg 1 ) resetTime $end
$var reg 1 * setValue $end
$var reg 1 + start_resume $end
$var reg 1 , stop $end
$var reg 1 - upTime $end
$scope module uut $end
$var wire 4 . Alm_hour0_d [3:0] $end
$var wire 4 / Alm_hour1_d [3:0] $end
$var wire 4 0 Alm_min0_d [3:0] $end
$var wire 4 1 Alm_min1_d [3:0] $end
$var wire 4 2 St_hour0 [3:0] $end
$var wire 4 3 St_hour1 [3:0] $end
$var wire 4 4 St_min0 [3:0] $end
$var wire 4 5 St_min1 [3:0] $end
$var wire 4 6 W_hour0 [3:0] $end
$var wire 4 7 W_hour1 [3:0] $end
$var wire 4 8 W_min0 [3:0] $end
$var wire 4 9 W_min1 [3:0] $end
$var wire 1 ! alarmBeep $end
$var wire 1 : clk $end
$var wire 7 ; d0 [6:0] $end
$var wire 7 < d1 [6:0] $end
$var wire 7 = d2 [6:0] $end
$var wire 7 > d3 [6:0] $end
$var wire 3 ? mode [2:0] $end
$var wire 1 @ nextd $end
$var wire 1 A resetTime $end
$var wire 1 B setValue $end
$var wire 1 C start_resume $end
$var wire 1 D stop $end
$var wire 1 E upTime $end
$var reg 4 F Alm_hour0 [3:0] $end
$var reg 4 G Alm_hour1 [3:0] $end
$var reg 4 H Alm_min0 [3:0] $end
$var reg 4 I Alm_min1 [3:0] $end
$var reg 4 J dis0 [3:0] $end
$var reg 4 K dis1 [3:0] $end
$var reg 4 L dis2 [3:0] $end
$var reg 4 M dis3 [3:0] $end
$scope module timeset $end
$var wire 1 @ nextDigit $end
$var wire 1 A reset $end
$var wire 1 B start $end
$var wire 1 E up $end
$var reg 1 N changeTime $end
$var reg 2 O currNum [1:0] $end
$var reg 4 P h0 [3:0] $end
$var reg 4 Q h1 [3:0] $end
$var reg 4 R m0 [3:0] $end
$var reg 4 S m1 [3:0] $end
$upscope $end
$scope module alm $end
$var wire 1 A alarmReset $end
$var wire 1 B alarmSet $end
$var wire 1 : clk $end
$var wire 4 T curHour0 [3:0] $end
$var wire 4 U curHour1 [3:0] $end
$var wire 4 V curMin0 [3:0] $end
$var wire 4 W curMin1 [3:0] $end
$var reg 1 X alarm $end
$var reg 4 Y disH0 [3:0] $end
$var reg 4 Z disH1 [3:0] $end
$var reg 4 [ disM0 [3:0] $end
$var reg 4 \ disM1 [3:0] $end
$var reg 4 ] savHour0 [3:0] $end
$var reg 4 ^ savHour1 [3:0] $end
$var reg 4 _ savMin0 [3:0] $end
$var reg 4 ` savMin1 [3:0] $end
$upscope $end
$scope module stopwatch $end
$var wire 1 a clk $end
$var wire 4 b milSec0 [3:0] $end
$var wire 4 c min0 [3:0] $end
$var wire 1 d min0clk $end
$var wire 1 e reset $end
$var wire 4 f sec0 [3:0] $end
$var wire 1 g sec0clk $end
$var wire 4 h sec1 [3:0] $end
$var wire 1 i sec1clk $end
$var wire 1 j start_resume $end
$var wire 1 k stop $end
$scope module MIL0 $end
$var wire 1 a clk $end
$var wire 1 e reset $end
$var wire 1 j start_resume $end
$var wire 1 k stop $end
$var reg 1 l cout $end
$var reg 4 m current [3:0] $end
$var reg 4 n next [3:0] $end
$var reg 4 o number [3:0] $end
$upscope $end
$scope module SEC0 $end
$var wire 1 g clk $end
$var wire 1 e reset $end
$var wire 1 j start_resume $end
$var wire 1 k stop $end
$var reg 1 p cout $end
$var reg 4 q current [3:0] $end
$var reg 4 r next [3:0] $end
$var reg 4 s number [3:0] $end
$upscope $end
$scope module SEC1 $end
$var wire 1 i clk $end
$var wire 1 e reset $end
$var wire 1 j start_resume $end
$var wire 1 k stop $end
$var reg 1 t cout $end
$var reg 4 u current [3:0] $end
$var reg 4 v next [3:0] $end
$var reg 4 w number [3:0] $end
$upscope $end
$scope module MIN0 $end
$var wire 1 d clk $end
$var wire 1 e reset $end
$var wire 1 j start_resume $end
$var wire 1 k stop $end
$var reg 1 x cout $end
$var reg 4 y current [3:0] $end
$var reg 4 z next [3:0] $end
$var reg 4 { number [3:0] $end
$upscope $end
$upscope $end
$scope module watch $end
$var wire 1 : clk $end
$var wire 1 | h0clk $end
$var wire 1 } h1clk $end
$var wire 4 ~ hr0 [3:0] $end
$var wire 4 !" hr1 [3:0] $end
$var wire 4 "" min0 [3:0] $end
$var wire 4 #" min1 [3:0] $end
$var wire 1 $" min1clk $end
$var wire 1 A reset $end
$var wire 1 B setTime $end
$var wire 1 C start_resume $end
$var wire 1 D stop $end
$scope module Min0 $end
$var wire 1 : clk $end
$var wire 1 A reset $end
$var wire 1 C start_resume $end
$var wire 1 D stop $end
$var reg 1 %" cout $end
$var reg 4 &" current [3:0] $end
$var reg 4 '" next [3:0] $end
$var reg 4 (" number [3:0] $end
$upscope $end
$scope module Min1 $end
$var wire 1 $" clk $end
$var wire 1 A reset $end
$var wire 1 C start_resume $end
$var wire 1 D stop $end
$var reg 1 )" cout $end
$var reg 4 *" current [3:0] $end
$var reg 4 +" next [3:0] $end
$var reg 4 ," number [3:0] $end
$upscope $end
$scope module Hr0 $end
$var wire 1 | clk $end
$var wire 1 A reset $end
$var wire 1 C start_resume $end
$var wire 1 D stop $end
$var reg 1 -" cout $end
$var reg 4 ." current [3:0] $end
$var reg 4 /" next [3:0] $end
$var reg 4 0" number [3:0] $end
$upscope $end
$scope module Hr1 $end
$var wire 1 } clk $end
$var wire 1 A reset $end
$var wire 1 C start_resume $end
$var wire 1 D stop $end
$var reg 1 1" cout $end
$var reg 4 2" current [3:0] $end
$var reg 4 3" next [3:0] $end
$var reg 4 4" number [3:0] $end
$upscope $end
$upscope $end
$scope module first $end
$var wire 4 5" number [3:0] $end
$var reg 1 6" A $end
$var reg 1 7" B $end
$var reg 1 8" C $end
$var reg 1 9" D $end
$var reg 1 :" E $end
$var reg 1 ;" F $end
$var reg 1 <" G $end
$upscope $end
$scope module second $end
$var wire 4 =" number [3:0] $end
$var reg 1 >" A $end
$var reg 1 ?" B $end
$var reg 1 @" C $end
$var reg 1 A" D $end
$var reg 1 B" E $end
$var reg 1 C" F $end
$var reg 1 D" G $end
$upscope $end
$scope module third $end
$var wire 4 E" number [3:0] $end
$var reg 1 F" A $end
$var reg 1 G" B $end
$var reg 1 H" C $end
$var reg 1 I" D $end
$var reg 1 J" E $end
$var reg 1 K" F $end
$var reg 1 L" G $end
$upscope $end
$scope module fourth $end
$var wire 4 M" number [3:0] $end
$var reg 1 N" A $end
$var reg 1 O" B $end
$var reg 1 P" C $end
$var reg 1 Q" D $end
$var reg 1 R" E $end
$var reg 1 S" F $end
$var reg 1 T" G $end
$upscope $end
$upscope $end
$upscope $end
$enddefinitions $end
#0
$dumpvars
xT"
xS"
xR"
xQ"
xP"
xO"
xN"
bx M"
xL"
xK"
xJ"
xI"
xH"
xG"
xF"
bx E"
xD"
xC"
xB"
xA"
x@"
x?"
x>"
bx ="
x<"
x;"
x:"
x9"
x8"
x7"
x6"
bx 5"
bx 4"
b0 3"
bx 2"
01"
bx 0"
b0 /"
bx ."
0-"
bx ,"
b0 +"
bx *"
0)"
bx ("
b0 '"
bx &"
0%"
0$"
bx #"
bx ""
bx !"
bx ~
0}
0|
bx {
bx z
bx y
xx
bx w
bx v
bx u
xt
bx s
bx r
bx q
xp
bx o
bx n
bx m
xl
zk
zj
xi
bx h
xg
bx f
ze
xd
bx c
bx b
za
bx `
bx _
bx ^
bx ]
bx \
bx [
bx Z
bx Y
xX
bx W
bx V
bx U
bx T
b0 S
b0 R
b0 Q
b0 P
b0 O
0N
bx M
bx L
bx K
bx J
bx I
bx H
bx G
bx F
0E
xD
xC
0B
1A
x@
b0 ?
bx >
bx =
bx <
bx ;
0:
bx 9
bx 8
bx 7
bx 6
b0 5
b0 4
b0 3
b0 2
bx 1
bx 0
bx /
bx .
0-
x,
x+
0*
1)
x(
b0 '
0&
bx %
bx $
bx #
bx "
x!
$end
#1
b0 ("
b0 8
b0 ""
b0 ^
b0 ]
b0 `
b0 _
b0 &"
1&
1:
#2
0&
0:
#3
0X
0!
0T"
1S"
1R"
1Q"
1P"
1O"
1N"
b111111 "
b111111 ;
b0 H
b0 V
b0 J
b0 M"
1&
1:
#4
0&
0:
#5
1&
1:
#6
0&
0:
#7
1&
1:
#8
0&
0:
#9
1&
1:
#10
0&
0:
#11
1&
1:
#12
0&
0:
#13
1&
1:
#14
0&
0:
#15
1&
1:
#16
0&
0:
#17
1&
1:
#18
0&
0:
#19
1&
1:
#20
0&
0:
#21
1&
1:
#22
0&
0:
#23
1&
1:
#24
0&
0:
#25
1&
1:
#26
0&
0:
#27
1&
1:
#28
0&
0:
#29
1&
1:
#30
0&
0:
#31
1&
1:
#32
0&
0:
#33
1&
1:
#34
0&
0:
#35
1&
1:
#36
0&
0:
#37
1&
1:
#38
0&
0:
#39
1&
1:
#40
0&
0:
#41
1&
1:
#42
0&
0:
#43
1&
1:
#44
0&
0:
#45
1&
1:
#46
0&
0:
#47
1&
1:
#48
0&
0:
#49
1&
1:
#50
0&
0:
#51
1&
1:
#52
0&
0:
#53
1&
1:
#54
0&
0:
#55
1&
1:
#56
0&
0:
#57
1&
1:
#58
0&
0:
#59
1&
1:
#60
0&
0:
#61
1&
1:
#62
0&
0:
#63
1&
1:
#64
0&
0:
#65
1&
1:
#66
0&
0:
#67
1&
1:
#68
0&
0:
#69
1&
1:
#70
0&
0:
#71
1&
1:
#72
0&
0:
#73
1&
1:
#74
0&
0:
#75
1&
1:
#76
0&
0:
#77
1&
1:
#78
0&
0:
#79
1&
1:
#80
0&
0:
#81
1&
1:
#82
0&
0:
#83
1&
1:
#84
0&
0:
#85
1&
1:
#86
0&
0:
#87
1&
1:
#88
0&
0:
#89
1&
1:
#90
0&
0:
#91
1&
1:
#92
0&
0:
#93
1&
1:
#94
0&
0:
#95
1&
1:
#96
0&
0:
#97
1&
1:
#98
0&
0:
#99
1&
1:
#100
b0 4"
b0 7
b0 !"
b1 3"
11"
b0 2"
b0 0"
b0 6
b0 ~
b1 /"
1-"
1}
b0 ."
b0 ,"
b0 9
b0 #"
b1 +"
1)"
1|
b0 *"
b1 '"
1%"
1$"
1+
1C
0)
0A
0&
0:
#101
b1 ("
b1 8
b1 ""
b10 '"
0%"
0$"
0L"
1K"
1J"
1I"
1H"
1G"
1F"
b111111 #
b111111 <
0D"
1C"
1B"
1A"
1@"
1?"
1>"
b111111 $
b111111 =
0<"
1;"
1:"
19"
18"
17"
16"
b111111 %
b111111 >
b0 Z
b0 /
b0 Y
b0 .
b0 \
b0 1
b0 [
b0 0
b1 &"
b0 I
b0 W
b0 F
b0 T
b0 G
b0 U
b0 K
b0 E"
b0 L
b0 ="
b0 M
b0 5"
1&
1:
#102
0&
0:
#103
b10 ("
b10 8
b10 ""
b11 '"
0S"
0R"
0Q"
0N"
b110 "
b110 ;
b10 &"
b1 H
b1 V
b1 J
b1 M"
1&
1:
#104
0&
0:
#105
b11 ("
b11 8
b11 ""
b100 '"
1T"
1R"
1Q"
0P"
1N"
b1011011 "
b1011011 ;
b11 &"
b10 H
b10 V
b10 J
b10 M"
1&
1:
#106
0&
0:
#107
b100 ("
b100 8
b100 ""
b101 '"
0R"
1P"
b1001111 "
b1001111 ;
b100 &"
b11 H
b11 V
b11 J
b11 M"
1&
1:
#108
0&
0:
#109
b101 ("
b101 8
b101 ""
b110 '"
1S"
0Q"
0N"
b1100110 "
b1100110 ;
b101 &"
b100 H
b100 V
b100 J
b100 M"
1&
1:
#110
0T"
1R"
1Q"
1N"
b111111 "
b111111 ;
b0 J
b0 M"
0&
0:
b10 '
b10 ?
#111
b110 ("
b110 8
b110 ""
b111 '"
b110 &"
1&
1:
#112
0&
0:
#113
b111 ("
b111 8
b111 ""
b1000 '"
b111 &"
1&
1:
#114
0&
0:
#115
b1000 ("
b1000 8
b1000 ""
b1001 '"
b1000 &"
1&
1:
#116
0&
0:
#117
b1001 ("
b1001 8
b1001 ""
b0 '"
b1001 &"
1&
1:
#118
0&
0:
#119
b1 ,"
b1 9
b1 #"
b10 +"
0)"
0|
b1 *"
b0 ("
b0 8
b0 ""
b1 '"
1%"
1$"
b0 &"
1&
1:
#120
1N
0&
0:
1*
1B
#121
b1 ("
b1 8
b1 ""
b10 '"
0%"
0$"
b100 _
b1 &"
b0 H
b0 V
1&
1:
#122
0&
0:
#123
b10 ("
b10 8
b10 ""
b11 '"
b10 &"
b0 _
1&
1:
#124
0&
0:
#125
b11 ("
b11 8
b11 ""
b100 '"
b11 &"
1&
1:
#126
0&
0:
#127
b100 ("
b100 8
b100 ""
b101 '"
b100 &"
1&
1:
#128
0&
0:
#129
b101 ("
b101 8
b101 ""
b110 '"
b101 &"
1&
1:
#130
b1 R
b1 4
0&
0:
1-
1E
#131
b110 ("
b110 8
b110 ""
b111 '"
0S"
0R"
0Q"
0N"
b110 "
b110 ;
b110 &"
b1 H
b1 V
b1 J
b1 M"
1&
1:
#132
0&
0:
#133
b111 ("
b111 8
b111 ""
b1000 '"
b1 _
b111 &"
1&
1:
#134
0&
0:
#135
b1000 ("
b1000 8
b1000 ""
b1001 '"
b1000 &"
1&
1:
#136
0&
0:
#137
b1001 ("
b1001 8
b1001 ""
b0 '"
b1001 &"
1&
1:
#138
0&
0:
#139
b10 ,"
b10 9
b10 #"
b11 +"
b10 *"
b0 ("
b0 8
b0 ""
b1 '"
1%"
1$"
b0 &"
1&
1:
#140
0&
0:
0-
0E
#141
b1 ("
b1 8
b1 ""
b10 '"
0%"
0$"
b1 &"
1&
1:
#142
0&
0:
#143
b10 ("
b10 8
b10 ""
b11 '"
b10 &"
1&
1:
#144
0&
0:
#145
b11 ("
b11 8
b11 ""
b100 '"
b11 &"
1&
1:
#146
0&
0:
#147
b100 ("
b100 8
b100 ""
b101 '"
b100 &"
1&
1:
#148
0&
0:
#149
b101 ("
b101 8
b101 ""
b110 '"
b101 &"
1&
1:
#150
b10 R
b10 4
0&
0:
1-
1E
#151
b110 ("
b110 8
b110 ""
b111 '"
1T"
1R"
1Q"
0P"
1N"
b1011011 "
b1011011 ;
b110 &"
b10 H
b10 V
b10 J
b10 M"
1&
1:
#152
0&
0:
#153
b111 ("
b111 8
b111 ""
b1000 '"
b10 _
b111 &"
1&
1:
#154
0&
0:
#155
b1000 ("
b1000 8
b1000 ""
b1001 '"
b1000 &"
1&
1:
#156
0&
0:
#157
b1001 ("
b1001 8
b1001 ""
b0 '"
b1001 &"
1&
1:
