verilog/vendingmachine/vending.v
module vending (
  output drink,
  input coin5, coin10, reset, clk
);

reg [1:0] cst, nst;
reg drink;

parameter hasCoin0 = 2'b00,
  hasCoin5 = 2'b01,
  hasCoin10 = 2'b10,
  hasCoin15 = 2'b11;

always @(cst or coin5 or coin10)
begin
  case (cst)
    hasCoin0: 
      if(coin5 == 1'b1 && coin10 == 1'b0)
      begin
        nst = hasCoin5;
        drink = 1'b0;
      end
      else if(coin5 == 1'b0 && coin10 == 1'b1)
      begin
        nst = hasCoin10;
        drink = 1'b0;
      end
      else if(coin5 == 1'b1 && coin10 == 1'b1)
      begin
        nst = hasCoin15;
        drink = 1'b0;
      end
      else //coin5 = 0, coin10 = 0
      begin
        nst = hasCoin0;
        drink = 1'b0;
      end

    hasCoin5:
      if(coin5 == 1'b1 && coin10 == 1'b0)
      begin
        nst = hasCoin10;
        drink = 1'b0;
      end
      else if(coin5 == 1'b0 && coin10 == 1'b1)
      begin
        nst = hasCoin15;
        drink = 1'b0;
      end
      else if(coin5 == 1'b1 && coin10 == 1'b1)
      begin
        //don't cares
      end
      else
      begin
        nst = hasCoin0;
        drink = 1'b0;
      end

    hasCoin10:
      if(coin5 == 1'b1 && coin10 == 1'b0)
      begin
        nst = hasCoin15;
        drink = 1'b0;
      end
      else if(coin5 == 1'b0 && coin10 == 1'b1)
      begin
        nst = hasCoin15;
        drink = 1'b0;
      end
      else if(coin5 == 1'b1 && coin10 == 1'b1)
      begin
        //don't cares
      end
      else
      begin
        nst = hasCoin10;
        drink = 1'b0;
      end
    hasCoin15:
    begin
      nst = hasCoin0;
      drink = 1'b1;
    end
    default: nst = hasCoin0;
  endcase
end

always @ (posedge clk)
begin
  begin
    if(reset)
      cst <= hasCoin0;
    else
      cst <= nst;
  end
end

endmodule

verilog/vendingmachine/vending_test.v
`include "vending.v"

module vending_test;
reg coin5, coin10, reset, clk;
wire drink;

vending m(drink, coin5, coin10,reset,clk);

initial begin
  coin5 = 0;
  coin10 = 0;
  reset = 1;
  clk = 0;
  $dumpfile("vending.vcd");
  $dumpvars(0,vending_test);
  forever begin
    #10 clk = ~clk;
  end 
end

initial begin
  #20 reset = 0;
  #20 coin5 = 0; coin10 = 1;
  #20 coin5 = 1; coin10 = 0;
  #20 coin5 = 0; coin10 = 0;
  #20 coin5 = 1; coin10 = 1;
  #20 coin5 = 0; coin10 = 0;
  #5 coin5 = 0; coin10 = 0;
  #10 coin5 = 1; coin10 = 0;
  #70 coin5 = 0; coin10 = 0;

  #100 $finish;
end

initial begin
  $monitor ($time," coin5: %b ",coin5, "coin10: %b ", coin10, " drink: %b", drink);
end
  
endmodule

verilog/vendingmachine/vending.vcd
$date
	Sat May  9 23:08:36 2015
$end
$version
	Icarus Verilog
$end
$timescale
	1s
$end
$scope module vending_test $end
$var wire 1 ! drink $end
$var reg 1 " clk $end
$var reg 1 # coin10 $end
$var reg 1 $ coin5 $end
$var reg 1 % reset $end
$scope module m $end
$var wire 1 & clk $end
$var wire 1 ' coin10 $end
$var wire 1 ( coin5 $end
$var wire 1 ) reset $end
$var reg 2 * cst [1:0] $end
$var reg 1 + drink $end
$var reg 2 , nst [1:0] $end
$upscope $end
$upscope $end
$enddefinitions $end
#0
$dumpvars
b0 ,
x+
bx *
1)
0(
0'
0&
1%
0$
0#
0"
x!
$end
#10
0+
0!
b0 *
1"
1&
#20
0"
0&
0%
0)
#30
1"
1&
#40
b10 ,
0"
0&
1#
1'
#50
b11 ,
b10 *
1"
1&
#60
0"
0&
0#
0'
1$
1(
#70
1+
1!
b0 ,
b11 *
1"
1&
#80
0"
0&
0$
0(
#90
0+
0!
b0 *
1"
1&
#100
b11 ,
0"
0&
1#
1'
1$
1(
#110
1+
1!
b0 ,
b11 *
1"
1&
#120
0"
0&
0#
0'
0$
0(
#130
0+
0!
b0 *
1"
1&
#135
b1 ,
1$
1(
#140
0"
0&
#150
b10 ,
b1 *
1"
1&
#160
0"
0&
#170
b11 ,
b10 *
1"
1&
#180
0"
0&
#190
1+
1!
b0 ,
b11 *
1"
1&
#200
0"
0&
#205
0$
0(
#210
0+
0!
b0 *
1"
1&
