final/watch/Mod13Counter.v
//since modulo is expensive(is it?)
//do it manually
//first digit of hour display
//should have 24/12 mode input?????
module Mod13Counter(
  output[3:0] number,
  output cout,
  input start_resume,reset, stop, clk
);

reg [3:0] current, next;
reg [3:0] number;
reg cout;

parameter zero =4'b0000,
  one=4'b0001,
  two=4'b0010,
  three=4'b0011,
  four=4'b0100,
  five=4'b0101,
  six=4'b0110,
  seven=4'b0111,
  eight=4'b1000,
  nine=4'b1001,
  ten=4'b1010,
  eleven = 4'b1011,
  twelve = 4'b1100;
  

always @(current or start_resume or reset or stop) 
begin
  if(start_resume==1 && current != twelve)
  begin
    if  (current == zero)
    begin
      cout = 1;
    end
    else
    begin
      cout = 0;
    end
    next=current + 1;
    number=current%10;
  end
  else if(start_resume==0)
  begin
    cout = 0;
    next=current;
    number=current%10;
  end
  else if(stop==1)
  begin
    cout = 0;
    next=current;
    number=current%10;
  end
  else if(reset==1) 
  begin
    cout = 0;
    next=zero;
    number=current%10;
  end

  //change this to for counter of different modulo
  if(current == twelve)
  begin
    next = zero;
    cout = 0;
    number = current%10;
  end

end

always @(posedge clk)
begin
  begin
    if(reset==1)
      current <= zero;
    else
      current <= next;
  end
end
endmodule

final/watch/ModCounter_test.v
`timescale 1ns/10ps
`include "./Mod13Counter.v"

module stopwatch_test;
wire [3:0] number;
wire cout;
reg start_resume, reset, stop, clk;

Mod13Counter uut(number,cout,start_resume,reset,stop,clk);

initial begin
  start_resume = 0;
  reset = 1;
  clk = 0;
  $dumpfile("watch.vcd");
  $dumpvars(0,stopwatch_test);
  forever begin
    #10 clk = ~clk;
  end 
end 

initial begin
  #100
  begin
    start_resume = 1;
    reset = 0;
  end
  #600 $finish;
end 

initial begin
  $monitor ($time, "  number : %b cout: %b", number,cout);
end

endmodule

final/watch/watch.vcd
$date
	Tue Jun  9 16:42:04 2015
$end
$version
	Icarus Verilog
$end
$timescale
	10ps
$end
$scope module stopwatch_test $end
$var wire 1 ! cout $end
$var wire 4 " number [3:0] $end
$var reg 1 # clk $end
$var reg 1 $ reset $end
$var reg 1 % start_resume $end
$var reg 1 & stop $end
$scope module uut $end
$var wire 1 ' clk $end
$var wire 1 ( reset $end
$var wire 1 ) start_resume $end
$var wire 1 * stop $end
$var reg 1 + cout $end
$var reg 4 , current [3:0] $end
$var reg 4 - next [3:0] $end
$var reg 4 . number [3:0] $end
$upscope $end
$upscope $end
$enddefinitions $end
#0
$dumpvars
bx .
bx -
bx ,
0+
x*
0)
1(
0'
x&
0%
1$
0#
bx "
0!
$end
#1000
b0 .
b0 "
b0 -
b0 ,
1#
1'
#2000
0#
0'
#3000
1#
1'
#4000
0#
0'
#5000
1#
1'
#6000
0#
0'
#7000
1#
1'
#8000
0#
0'
#9000
1#
1'
#10000
b1 -
1+
1!
0#
0'
0$
0(
1%
1)
#11000
b1 .
b1 "
b10 -
0+
0!
b1 ,
1#
1'
#12000
0#
0'
#13000
b10 .
b10 "
b11 -
b10 ,
1#
1'
#14000
0#
0'
#15000
b11 .
b11 "
b100 -
b11 ,
1#
1'
#16000
0#
0'
#17000
b100 .
b100 "
b101 -
b100 ,
1#
1'
#18000
0#
0'
#19000
b101 .
b101 "
b110 -
b101 ,
1#
1'
#20000
0#
0'
#21000
b110 .
b110 "
b111 -
b110 ,
1#
1'
#22000
0#
0'
#23000
b111 .
b111 "
b1000 -
b111 ,
1#
1'
#24000
0#
0'
#25000
b1000 .
b1000 "
b1001 -
b1000 ,
1#
1'
#26000
0#
0'
#27000
b1001 .
b1001 "
b1010 -
b1001 ,
1#
1'
#28000
0#
0'
#29000
b0 .
b0 "
b1011 -
b1010 ,
1#
1'
#30000
0#
0'
#31000
b1 .
b1 "
b1100 -
b1011 ,
1#
1'
#32000
0#
0'
#33000
b10 .
b10 "
b0 -
b1100 ,
1#
1'
#34000
0#
0'
#35000
b0 .
b0 "
b1 -
1+
1!
b0 ,
1#
1'
#36000
0#
0'
#37000
b1 .
b1 "
b10 -
0+
0!
b1 ,
1#
1'
#38000
0#
0'
#39000
b10 .
b10 "
b11 -
b10 ,
1#
1'
#40000
0#
0'
#41000
b11 .
b11 "
b100 -
b11 ,
1#
1'
#42000
0#
0'
#43000
b100 .
b100 "
b101 -
b100 ,
1#
1'
#44000
0#
0'
#45000
b101 .
b101 "
b110 -
b101 ,
1#
1'
#46000
0#
0'
#47000
b110 .
b110 "
b111 -
b110 ,
1#
1'
#48000
0#
0'
#49000
b111 .
b111 "
b1000 -
b111 ,
1#
1'
#50000
0#
0'
#51000
b1000 .
b1000 "
b1001 -
b1000 ,
1#
1'
#52000
0#
0'
#53000
b1001 .
b1001 "
b1010 -
b1001 ,
1#
1'
#54000
0#
0'
#55000
b0 .
b0 "
b1011 -
b1010 ,
1#
1'
#56000
0#
0'
#57000
b1 .
b1 "
b1100 -
b1011 ,
1#
1'
#58000
0#
0'
#59000
b10 .
b10 "
b0 -
b1100 ,
1#
1'
#60000
0#
0'
#61000
b0 .
b0 "
b1 -
1+
1!
b0 ,
1#
1'
#62000
0#
0'
#63000
b1 .
b1 "
b10 -
0+
0!
b1 ,
1#
1'
#64000
0#
0'
#65000
b10 .
b10 "
b11 -
b10 ,
1#
1'
#66000
0#
0'
#67000
b11 .
b11 "
b100 -
b11 ,
1#
1'
#68000
0#
0'
#69000
b100 .
b100 "
b101 -
b100 ,
1#
1'
