final/settime/SetTime.v
//based on mode, should use diffrent modulous for time???
//NO! Alarm and clock use the same time scale.
//How should we return output?
module SetTime (
  output[3:0] h1, h0, m1, m0,
  input start, reset, nextDigit, up
);

reg h1, h0, m1, m0;
//wire current, next;
reg[1:0] currNum;
reg changeTime;

always @(posedge up or posedge reset)
begin
  begin
    if  (reset == 1)
    begin
      currNum <= 0;
      changeTime <= 0;
      h1 <= 0;
      h0 <= 0;
      m1 <= 0;
      m0 <= 0;
    end
    else if  (currNum == 3 && changeTime==1)
      h1 <= (h1 + 1)%2; //TODO should change this depending on time mode
    else if  (currNum == 2&& changeTime==1)
      h0 <= (h0 + 1)%10; //can use 10 modulous instead of 12 because there is not cout
    else if  (currNum == 1&& changeTime==1)
      m1 <= (m1 + 1)%6;
    else if  (currNum == 0&& changeTime==1)
      m0 <= (m0 + 1)%10;
  end
end

always @(posedge nextDigit)
begin
  begin
    if  (currNum == 3)
      currNum <= 0;
    else
      currNum <= currNum + 1;
  end
end

//odd number of start will changeTime,
//even number of start will not
always @(posedge start)
begin
  changeTime <= ~changeTime;
end

endmodule

final/settime/SetTime_test.v
`include "./SetTime.v"

module SetTime_test;
wire [3:0] h1, h0, min1, min0;
reg start, reset, nextDigit, up;

SetTime uut(
  h1,h0,min1,min0,start,reset,nextDigit,up
);

initial begin
  start = 0;
  reset = 1;
  up = 0;
  $dumpfile("SetTime.vcd");
  $dumpvars(0,SetTime_test);
end 

initial begin
  #100
  begin
    reset <= 0;
    start <= 1;
  end
  #10 start = 0;
  #10 up = 1;
  #10 up = 1;
  #10 up = 0;
  #10 up = 1;
  #10 up = 0;
  #10 up = 1;
  #10 up = 0;
  #10 up = 1;
  #10 up = 0;
  #10 up = 1;
  #10 up = 0;
  #10 up = 0;
  #10 up = 1;
  #10 up = 0;
  #10 up = 1;
  #10 up = 0;
  #10 up = 1;
  #10 up = 0;
  #10 up = 1;
  #10 up = 0;
  #10 nextDigit = 1;
  #10 nextDigit = 0;
  #10 up = 1;
  #10 up = 1;
  #10 up = 0;
  #10 up = 1;
  #10 up = 0;
  #10 up = 1;
  #10 up = 0;
  #10 up = 1;
  #10 up = 0;
  #10 up = 1;
  #10 up = 0;
  #10 up = 0;
  #10 up = 1;
  #10 up = 0;
  #10 up = 1;
  #10 up = 0;
  #200 nextDigit = 1;
  #10 nextDigit = 0;
  #10 up = 1;
  #10 up = 1;
  #10 up = 0;
  #10 up = 1;
  #10 up = 0;
  #10 up = 1;
  #10 up = 0;
  #10 up = 1;
  #10 up = 0;
  #10 up = 1;
  #10 up = 0;
  #10 up = 1;
  #10 up = 0;
  #10 up = 1;
  #10 up = 0;
  #10 up = 1;
  #10 up = 0;
  #10 up = 1;
  #10 up = 0;
  #10 up = 1;
  #10 up = 0;
  #10 up = 0;
  #10 up = 1;
  #10 up = 0;
  #10 up = 1;
  #10 up = 0;
  #10 up = 1;
  #10 up = 0;
  #10 up = 1;
  #10 up = 0;
  #10 up = 1;
  #10 up = 0;
  #10 up = 1;
  #10 up = 0;
  #10 up = 1;
  #10 up = 0;
  #200 nextDigit = 1;
  #10 nextDigit = 0;
  #10 up = 1;
  #10 up = 0;
  #10 up = 1;
  #10 up = 0;
  #10 up = 1;
  #10 up = 0;
  #10 up = 1;
  #10 up = 0;
  #10 up = 1;
  #10 up = 0;

  #3000 $finish;
end 

endmodule

final/settime/SetTime.vcd
$date
	Fri Jun 12 22:49:37 2015
$end
$version
	Icarus Verilog
$end
$timescale
	1s
$end
$scope module SetTime_test $end
$var wire 4 ! h0 [3:0] $end
$var wire 4 " h1 [3:0] $end
$var wire 4 # min0 [3:0] $end
$var wire 4 $ min1 [3:0] $end
$var reg 1 % nextDigit $end
$var reg 1 & reset $end
$var reg 1 ' start $end
$var reg 1 ( up $end
$scope module uut $end
$var wire 1 ) nextDigit $end
$var wire 1 * reset $end
$var wire 1 + start $end
$var wire 1 , up $end
$var reg 1 - changeTime $end
$var reg 2 . currNum [1:0] $end
$var reg 4 / h0 [3:0] $end
$var reg 4 0 h1 [3:0] $end
$var reg 4 1 m0 [3:0] $end
$var reg 4 2 m1 [3:0] $end
$upscope $end
$upscope $end
$enddefinitions $end
#0
$dumpvars
b0 2
b0 1
b0 0
b0 /
b0 .
0-
0,
0+
1*
x)
0(
0'
1&
x%
b0 $
b0 #
b0 "
b0 !
$end
#100
1-
1'
1+
0&
0*
#110
0'
0+
#120
b1 1
b1 #
1(
1,
#140
0(
0,
#150
b10 1
b10 #
1(
1,
#160
0(
0,
#170
b11 1
b11 #
1(
1,
#180
0(
0,
#190
b100 1
b100 #
1(
1,
#200
0(
0,
#210
b101 1
b101 #
1(
1,
#220
0(
0,
#240
b110 1
b110 #
1(
1,
#250
0(
0,
#260
b111 1
b111 #
1(
1,
#270
0(
0,
#280
b1000 1
b1000 #
1(
1,
#290
0(
0,
#300
b1001 1
b1001 #
1(
1,
#310
0(
0,
#320
b1 .
1%
1)
#330
0%
0)
#340
b1 2
b1 $
1(
1,
#360
0(
0,
#370
b10 2
b10 $
1(
1,
#380
0(
0,
#390
b11 2
b11 $
1(
1,
#400
0(
0,
#410
b100 2
b100 $
1(
1,
#420
0(
0,
#430
b101 2
b101 $
1(
1,
#440
0(
0,
#460
b0 2
b0 $
1(
1,
#470
0(
0,
#480
b1 2
b1 $
1(
1,
#490
0(
0,
#690
b10 .
1%
1)
#700
0%
0)
#710
b1 /
b1 !
1(
1,
#730
0(
0,
#740
b10 /
b10 !
1(
1,
#750
0(
0,
#760
b11 /
b11 !
1(
1,
#770
0(
0,
#780
b100 /
b100 !
1(
1,
#790
0(
0,
#800
b101 /
b101 !
1(
1,
#810
0(
0,
#820
b110 /
b110 !
1(
1,
#830
0(
0,
#840
b111 /
b111 !
1(
1,
#850
0(
0,
#860
b1000 /
b1000 !
1(
1,
#870
0(
0,
#880
b1001 /
b1001 !
1(
1,
#890
0(
0,
#900
b0 /
b0 !
1(
1,
#910
0(
0,
#930
b1 /
b1 !
1(
1,
#940
0(
0,
#950
b10 /
b10 !
1(
1,
#960
0(
0,
#970
b11 /
b11 !
1(
1,
#980
0(
0,
#990
b100 /
b100 !
1(
1,
#1000
0(
0,
#1010
b101 /
b101 !
1(
1,
#1020
0(
0,
#1030
b110 /
b110 !
1(
1,
#1040
0(
0,
#1050
b111 /
b111 !
1(
1,
#1060
0(
0,
#1260
b11 .
1%
1)
#1270
0%
0)
#1280
b1 0
b1 "
1(
1,
#1290
0(
0,
#1300
b0 0
b0 "
1(
1,
#1310
0(
0,
#1320
b1 0
b1 "
1(
1,
#1330
0(
0,
#1340
b0 0
b0 "
1(
1,
#1350
0(
0,
#1360
b1 0
b1 "
1(
1,
#1370
0(
0,
