final/watchController/Mod10Counter.v
`ifndef MOD10_V
`define MOD10_V
module Mod10Counter(
  output[3:0] number,
  output cout,
  input start_resume,reset, stop, clk
);

reg [3:0] current, next;
reg [3:0] number;
reg cout;

parameter zero =4'b0000,
  one=4'b0001,
  two=4'b0010,
  three=4'b0011,
  four=4'b0100,
  five=4'b0101,
  six=4'b0110,
  seven=4'b0111,
  eight=4'b1000,
  nine=4'b1001;

always @(current or start_resume or reset or stop) 
begin
  if(start_resume==1 && current != nine)
  begin
    if  (current == zero)
    begin
      cout = 1;
    end
    else
    begin
      cout = 0;
    end
    next=current + 1;
    number=current;
  end
  else if(start_resume==0)
  begin
    cout = 0;
    next=current;
    number=current;
  end
  else if(stop==1)
  begin
    cout = 0;
    next=current;
    number=current;
  end
  else if(reset==1) 
  begin
    cout = 0;
    next=zero;
    number=current;
  end

  //change this to for counter of different modulo
  if(current == nine)
  begin
    next = zero;
    cout = 0;
    number = current;
  end

end

always @(posedge clk)
begin
  begin
    if(reset==1)
      current <= zero;
    else
      current <= next;
  end
end
endmodule
`endif

final/stopwatch/Mod6Counter.v
module Mod6Counter(
  output[3:0] number,
  output cout,
  input start_resume,reset, stop, clk
);

reg [3:0] current, next;
reg [3:0] number;
reg cout;

parameter zero =4'b0000,
  one=4'b0001,
  two=4'b0010,
  three=4'b0011,
  four=4'b0100,
  five=4'b0101,
  six=4'b0110,
  seven=4'b0111,
  eight=4'b1000,
  nine=4'b1001;

always @(current or start_resume or reset or stop) 
begin
  if(start_resume==1 && current != nine)
  begin
    if  (current == zero)
    begin
      cout = 1;
    end
    else
    begin
      cout = 0;
    end
    next=current + 1;
    number=current;
  end
  else if(start_resume==0)
  begin
    cout = 0;
    next=current;
    number=current;
  end
  else if(stop==1)
  begin
    cout = 0;
    next=current;
    number=current;
  end
  else if(reset==1) 
  begin
    cout = 0;
    next=zero;
    number=current;
  end

  //change this to for counter of different modulo
  if(current == five)
  begin
    next = zero;
    cout = 0;
    number = current;
  end

end

always @(posedge clk)
begin
  begin
    if(reset==1)
      current <= zero;
    else
      current <= next;
  end
end
endmodule

final/stopwatch/StopWatch.v
`include "./Mod10Counter.v"
`include "./Mod6Counter.v"

module StopWatch(
  output[3:0] min0, sec1, sec0, milSec0,
  input start_resume,reset, stop, clk
);
wire min0,sec1,sec0,milSec0;

wire min0clk, sec1clk, sec0clk;


//devide the clk and put it as input.
Mod10Counter MIL0(milSec0, sec0clk, start_resume,reset,stop,clk);
Mod10Counter SEC0(sec0, sec1clk, start_resume,reset,stop,sec0clk);
Mod6Counter SEC1(sec1, min0clk, start_resume,reset,stop,sec1clk);
Mod10Counter MIN0(min0,,start_resume,reset,stop,min0clk);

endmodule

final/stopwatch/StopWatch_test.v
`include "./StopWatch.v"

module StopWatch_test;
wire [3:0] min0, sec1, sec0, milSec0;
reg start_resume, reset, stop, clk;

StopWatch uut(
  min0,sec1,sec0,milSec0,start_resume,reset,stop,clk
);

initial begin
  start_resume = 1;
  reset = 1;
  clk = 0;
  $dumpfile("watch.vcd");
  $dumpvars(0,StopWatch_test);
  forever begin
    #1 clk = ~clk;
  end 
end 

initial begin
  #100
  begin
    reset <= 0;
    start_resume <= 1;
  end
  #3000 $finish;
end 

endmodule

final/stopwatch/watch.vcd
$date
	Fri Jun 12 21:22:37 2015
$end
$version
	Icarus Verilog
$end
$timescale
	1s
$end
$scope module StopWatch_test $end
$var wire 4 ! milSec0 [3:0] $end
$var wire 4 " min0 [3:0] $end
$var wire 4 # sec0 [3:0] $end
$var wire 4 $ sec1 [3:0] $end
$var reg 1 % clk $end
$var reg 1 & reset $end
$var reg 1 ' start_resume $end
$var reg 1 ( stop $end
$scope module uut $end
$var wire 1 ) clk $end
$var wire 4 * milSec0 [3:0] $end
$var wire 4 + min0 [3:0] $end
$var wire 1 , min0clk $end
$var wire 1 - reset $end
$var wire 4 . sec0 [3:0] $end
$var wire 1 / sec0clk $end
$var wire 4 0 sec1 [3:0] $end
$var wire 1 1 sec1clk $end
$var wire 1 2 start_resume $end
$var wire 1 3 stop $end
$scope module MIL0 $end
$var wire 1 ) clk $end
$var wire 1 - reset $end
$var wire 1 2 start_resume $end
$var wire 1 3 stop $end
$var reg 1 4 cout $end
$var reg 4 5 current [3:0] $end
$var reg 4 6 next [3:0] $end
$var reg 4 7 number [3:0] $end
$upscope $end
$scope module SEC0 $end
$var wire 1 / clk $end
$var wire 1 - reset $end
$var wire 1 2 start_resume $end
$var wire 1 3 stop $end
$var reg 1 8 cout $end
$var reg 4 9 current [3:0] $end
$var reg 4 : next [3:0] $end
$var reg 4 ; number [3:0] $end
$upscope $end
$scope module SEC1 $end
$var wire 1 1 clk $end
$var wire 1 - reset $end
$var wire 1 2 start_resume $end
$var wire 1 3 stop $end
$var reg 1 < cout $end
$var reg 4 = current [3:0] $end
$var reg 4 > next [3:0] $end
$var reg 4 ? number [3:0] $end
$upscope $end
$scope module MIN0 $end
$var wire 1 , clk $end
$var wire 1 - reset $end
$var wire 1 2 start_resume $end
$var wire 1 3 stop $end
$var reg 1 @ cout $end
$var reg 4 A current [3:0] $end
$var reg 4 B next [3:0] $end
$var reg 4 C number [3:0] $end
$upscope $end
$upscope $end
$upscope $end
$enddefinitions $end
#0
$dumpvars
bx C
b0 B
bx A
0@
bx ?
b0 >
bx =
0<
bx ;
b0 :
bx 9
08
bx 7
b0 6
bx 5
04
x3
12
01
bx 0
0/
bx .
1-
0,
bx +
bx *
0)
x(
1'
1&
0%
bx $
bx #
bx "
bx !
$end
#1
b0 C
b0 "
b0 +
b1 B
1@
b0 A
b0 ?
b0 $
b0 0
b1 >
1<
1,
b0 =
b0 ;
b0 #
b0 .
b1 :
18
11
b0 9
b0 7
b0 !
b0 *
b1 6
14
1/
b0 5
1%
1)
#2
0%
0)
#3
1%
1)
#4
0%
0)
#5
1%
1)
#6
0%
0)
#7
1%
1)
#8
0%
0)
#9
1%
1)
#10
0%
0)
#11
1%
1)
#12
0%
0)
#13
1%
1)
#14
0%
0)
#15
1%
1)
#16
0%
0)
#17
1%
1)
#18
0%
0)
#19
1%
1)
#20
0%
0)
#21
1%
1)
#22
0%
0)
#23
1%
1)
#24
0%
0)
#25
1%
1)
#26
0%
0)
#27
1%
1)
#28
0%
0)
#29
1%
1)
#30
0%
0)
#31
1%
1)
#32
0%
0)
#33
1%
1)
#34
0%
0)
#35
1%
1)
#36
0%
0)
#37
1%
1)
#38
0%
0)
#39
1%
1)
#40
0%
0)
#41
1%
1)
#42
0%
0)
#43
1%
1)
#44
0%
0)
#45
1%
1)
#46
0%
0)
#47
1%
1)
#48
0%
0)
#49
1%
1)
#50
0%
0)
#51
1%
1)
#52
0%
0)
#53
1%
1)
#54
0%
0)
#55
1%
1)
#56
0%
0)
#57
1%
1)
#58
0%
0)
#59
1%
1)
#60
0%
0)
#61
1%
1)
#62
0%
0)
#63
1%
1)
#64
0%
0)
#65
1%
1)
#66
0%
0)
#67
1%
1)
#68
0%
0)
#69
1%
1)
#70
0%
0)
#71
1%
1)
#72
0%
0)
#73
1%
1)
#74
0%
0)
#75
1%
1)
#76
0%
0)
#77
1%
1)
#78
0%
0)
#79
1%
1)
#80
0%
0)
#81
1%
1)
#82
0%
0)
#83
1%
1)
#84
0%
0)
#85
1%
1)
#86
0%
0)
#87
1%
1)
#88
0%
0)
#89
1%
1)
#90
0%
0)
#91
1%
1)
#92
0%
0)
#93
1%
1)
#94
0%
0)
#95
1%
1)
#96
0%
0)
#97
1%
1)
#98
0%
0)
#99
1%
1)
#100
0&
0-
0%
0)
#101
b1 7
b1 !
b1 *
b10 6
04
0/
b1 5
1%
1)
#102
0%
0)
#103
b10 7
b10 !
b10 *
b11 6
b10 5
1%
1)
#104
0%
0)
#105
b11 7
b11 !
b11 *
b100 6
b11 5
1%
1)
#106
0%
0)
#107
b100 7
b100 !
b100 *
b101 6
b100 5
1%
1)
#108
0%
0)
#109
b101 7
b101 !
b101 *
b110 6
b101 5
1%
1)
#110
0%
0)
#111
b110 7
b110 !
b110 *
b111 6
b110 5
1%
1)
#112
0%
0)
#113
b111 7
b111 !
b111 *
b1000 6
b111 5
1%
1)
#114
0%
0)
#115
b1000 7
b1000 !
b1000 *
b1001 6
b1000 5
1%
1)
#116
0%
0)
#117
b1001 7
b1001 !
b1001 *
b0 6
b1001 5
1%
1)
#118
0%
0)
#119
b1 ;
b1 #
b1 .
b10 :
08
01
b1 9
b0 7
b0 !
b0 *
b1 6
14
1/
b0 5
1%
1)
#120
0%
0)
#121
b1 7
b1 !
b1 *
b10 6
04
0/
b1 5
1%
1)
#122
0%
0)
#123
b10 7
b10 !
b10 *
b11 6
b10 5
1%
1)
#124
0%
0)
#125
b11 7
b11 !
b11 *
b100 6
b11 5
1%
1)
#126
0%
0)
#127
b100 7
b100 !
b100 *
b101 6
b100 5
1%
1)
#128
0%
0)
#129
b101 7
b101 !
b101 *
b110 6
b101 5
1%
1)
#130
0%
0)
#131
b110 7
b110 !
b110 *
b111 6
b110 5
1%
1)
#132
0%
0)
#133
b111 7
b111 !
b111 *
b1000 6
b111 5
1%
1)
#134
0%
0)
#135
b1000 7
b1000 !
b1000 *
b1001 6
b1000 5
1%
1)
#136
0%
0)
#137
b1001 7
b1001 !
b1001 *
b0 6
b1001 5
1%
1)
#138
0%
0)
#139
b10 ;
b10 #
b10 .
b11 :
b10 9
b0 7
b0 !
b0 *
b1 6
14
1/
b0 5
1%
1)
#140
0%
0)
#141
b1 7
b1 !
b1 *
b10 6
04
0/
b1 5
1%
1)
#142
0%
0)
#143
b10 7
b10 !
b10 *
b11 6
b10 5
1%
1)
#144
0%
0)
#145
b11 7
b11 !
b11 *
b100 6
b11 5
1%
1)
#146
0%
0)
#147
b100 7
b100 !
b100 *
b101 6
b100 5
1%
1)
#148
0%
0)
#149
b101 7
b101 !
b101 *
b110 6
b101 5
1%
1)
#150
0%
0)
#151
b110 7
b110 !
b110 *
b111 6
b110 5
1%
1)
#152
0%
0)
#153
b111 7
b111 !
b111 *
b1000 6
b111 5
1%
1)
#154
0%
0)
#155
b1000 7
b1000 !
b1000 *
b1001 6
b1000 5
1%
1)
#156
0%
0)
#157
b1001 7
b1001 !
b1001 *
b0 6
b1001 5
1%
1)
#158
0%
0)
#159
b11 ;
b11 #
b11 .
b100 :
b11 9
b0 7
b0 !
b0 *
b1 6
14
1/
b0 5
1%
1)
#160
0%
0)
#161
b1 7
b1 !
b1 *
b10 6
04
0/
b1 5
1%
1)
#162
0%
0)
#163
b10 7
b10 !
b10 *
b11 6
b10 5
1%
1)
#164
0%
0)
#165
b11 7
b11 !
b11 *
b100 6
b11 5
1%
1)
#166
0%
0)
#167
b100 7
b100 !
b100 *
b101 6
b100 5
1%
1)
#168
0%
0)
#169
b101 7
b101 !
b101 *
b110 6
b101 5
1%
1)
#170
0%
0)
#171
b110 7
b110 !
b110 *
b111 6
b110 5
1%
1)
#172
0%
0)
#173
b111 7
b111 !
b111 *
b1000 6
b111 5
1%
1)
#174
0%
0)
#175
b1000 7
b1000 !
b1000 *
b1001 6
b1000 5
1%
1)
#176
0%
0)
#177
b1001 7
b1001 !
b1001 *
b0 6
b1001 5
1%
1)
#178
0%
0)
#179
b100 ;
b100 #
b100 .
b101 :
b100 9
b0 7
b0 !
b0 *
b1 6
14
1/
b0 5
1%
1)
#180
0%
0)
#181
b1 7
b1 !
b1 *
b10 6
04
0/
b1 5
1%
1)
#182
0%
0)
#183
b10 7
b10 !
b10 *
b11 6
b10 5
1%
1)
#184
0%
0)
#185
b11 7
b11 !
b11 *
b100 6
b11 5
1%
1)
#186
0%
0)
#187
b100 7
b100 !
b100 *
b101 6
b100 5
1%
1)
#188
0%
0)
#189
b101 7
b101 !
b101 *
b110 6
b101 5
1%
1)
#190
0%
0)
#191
b110 7
b110 !
b110 *
b111 6
b110 5
1%
1)
#192
0%
0)
#193
b111 7
b111 !
b111 *
b1000 6
b111 5
1%
1)
#194
0%
0)
#195
b1000 7
b1000 !
b1000 *
b1001 6
b1000 5
1%
1)
#196
0%
0)
#197
b1001 7
b1001 !
b1001 *
b0 6
b1001 5
1%
1)
#198
0%
0)
#199
b101 ;
b101 #
b101 .
b110 :
b101 9
b0 7
b0 !
b0 *
b1 6
14
1/
b0 5
1%
1)
#200
0%
0)
#201
b1 7
b1 !
b1 *
b10 6
04
0/
b1 5
1%
1)
#202
0%
0)
#203
b10 7
b10 !
b10 *
b11 6
b10 5
1%
1)
#204
0%
0)
#205
b11 7
b11 !
b11 *
b100 6
b11 5
1%
1)
#206
0%
0)
#207
b100 7
b100 !
b100 *
b101 6
b100 5
1%
1)
#208
0%
0)
#209
b101 7
b101 !
b101 *
b110 6
b101 5
1%
1)
#210
0%
0)
#211
b110 7
b110 !
b110 *
b111 6
b110 5
1%
1)
#212
0%
0)
#213
b111 7
b111 !
b111 *
b1000 6
b111 5
1%
1)
#214
0%
0)
#215
b1000 7
b1000 !
b1000 *
b1001 6
b1000 5
1%
1)
#216
0%
0)
#217
b1001 7
b1001 !
b1001 *
b0 6
b1001 5
1%
1)
#218
0%
0)
#219
b110 ;
b110 #
b110 .
b111 :
b110 9
b0 7
b0 !
b0 *
b1 6
14
1/
b0 5
1%
1)
#220
0%
0)
#221
b1 7
b1 !
b1 *
b10 6
04
0/
b1 5
1%
1)
#222
0%
0)
#223
b10 7
b10 !
b10 *
b11 6
b10 5
1%
1)
#224
0%
0)
#225
b11 7
b11 !
b11 *
b100 6
b11 5
1%
1)
#226
0%
0)
#227
b100 7
b100 !
b100 *
b101 6
b100 5
1%
1)
#228
0%
0)
#229
b101 7
b101 !
b101 *
b110 6
b101 5
1%
1)
#230
0%
0)
#231
b110 7
b110 !
b110 *
b111 6
b110 5
1%
1)
#232
0%
0)
#233
b111 7
b111 !
b111 *
b1000 6
b111 5
1%
1)
#234
0%
0)
#235
b1000 7
b1000 !
b1000 *
b1001 6
b1000 5
1%
1)
#236
0%
0)
#237
b1001 7
b1001 !
b1001 *
b0 6
b1001 5
1%
1)
#238
0%
0)
#239
b111 ;
b111 #
b111 .
b1000 :
b111 9
b0 7
b0 !
b0 *
b1 6
14
1/
b0 5
1%
1)
#240
0%
0)
#241
b1 7
b1 !
b1 *
b10 6
04
0/
b1 5
1%
1)
#242
0%
0)
#243
b10 7
b10 !
b10 *
b11 6
b10 5
1%
1)
#244
0%
0)
#245
b11 7
b11 !
b11 *
b100 6
b11 5
1%
1)
#246
0%
0)
#247
b100 7
b100 !
b100 *
b101 6
b100 5
1%
1)
#248
0%
0)
#249
b101 7
b101 !
b101 *
b110 6
b101 5
1%
1)
#250
0%
0)
#251
b110 7
b110 !
b110 *
b111 6
b110 5
1%
1)
#252
0%
0)
#253
b111 7
b111 !
b111 *
b1000 6
b111 5
1%
1)
#254
0%
0)
#255
b1000 7
b1000 !
b1000 *
b1001 6
b1000 5
1%
1)
#256
0%
0)
#257
b1001 7
b1001 !
b1001 *
b0 6
b1001 5
1%
1)
#258
0%
0)
#259
b1000 ;
b1000 #
b1000 .
b1001 :
b1000 9
b0 7
b0 !
b0 *
b1 6
14
1/
b0 5
1%
1)
#260
0%
0)
#261
b1 7
b1 !
b1 *
b10 6
04
0/
b1 5
1%
1)
#262
0%
0)
#263
b10 7
b10 !
b10 *
b11 6
b10 5
1%
1)
#264
0%
0)
#265
b11 7
b11 !
b11 *
b100 6
b11 5
1%
1)
#266
0%
0)
#267
b100 7
b100 !
b100 *
b101 6
b100 5
1%
1)
#268
0%
0)
#269
b101 7
b101 !
b101 *
b110 6
b101 5
1%
1)
#270
0%
0)
#271
b110 7
b110 !
b110 *
b111 6
b110 5
1%
1)
#272
0%
0)
#273
b111 7
b111 !
b111 *
b1000 6
b111 5
1%
1)
#274
0%
0)
#275
b1000 7
b1000 !
b1000 *
b1001 6
b1000 5
1%
1)
#276
0%
0)
#277
b1001 7
b1001 !
b1001 *
b0 6
b1001 5
1%
1)
#278
0%
0)
#279
b1001 ;
b1001 #
b1001 .
b0 :
b1001 9
b0 7
b0 !
b0 *
b1 6
14
1/
b0 5
1%
1)
#280
0%
0)
#281
b1 7
b1 !
b1 *
b10 6
04
0/
b1 5
1%
1)
#282
0%
0)
#283
b10 7
b10 !
b10 *
b11 6
b10 5
1%
1)
#284
0%
0)
#285
b11 7
b11 !
b11 *
b100 6
b11 5
1%
1)
#286
0%
0)
#287
b100 7
b100 !
b100 *
b101 6
b100 5
1%
1)
#288
0%
0)
#289
b101 7
b101 !
b101 *
b110 6
b101 5
1%
1)
#290
0%
0)
#291
b110 7
b110 !
b110 *
b111 6
b110 5
1%
1)
#292
0%
0)
#293
b111 7
b111 !
b111 *
b1000 6
b111 5
1%
1)
#294
0%
0)
#295
b1000 7
b1000 !
b1000 *
b1001 6
b1000 5
1%
1)
#296
0%
0)
#297
b1001 7
b1001 !
b1001 *
b0 6
b1001 5
1%
1)
#298
0%
0)
#299
b1 ?
b1 $
b1 0
b10 >
0<
0,
b1 =
b0 ;
b0 #
b0 .
b1 :
18
11
b0 9
b0 7
b0 !
b0 *
b1 6
14
1/
b0 5
1%
1)
#300
0%
0)
#301
b1 7
b1 !
b1 *
b10 6
04
0/
b1 5
1%
1)
#302
0%
0)
#303
b10 7
b10 !
b10 *
b11 6
b10 5
1%
1)
#304
0%
0)
#305
b11 7
b11 !
b11 *
b100 6
b11 5
1%
1)
#306
0%
0)
#307
b100 7
b100 !
b100 *
b101 6
b100 5
1%
1)
#308
0%
0)
#309
b101 7
b101 !
b101 *
b110 6
b101 5
1%
1)
#310
0%
0)
#311
b110 7
b110 !
b110 *
b111 6
b110 5
1%
1)
#312
0%
0)
#313
b111 7
b111 !
b111 *
b1000 6
b111 5
1%
1)
#314
0%
0)
#315
b1000 7
b1000 !
b1000 *
b1001 6
b1000 5
1%
1)
#316
0%
0)
#317
b1001 7
b1001 !
b1001 *
b0 6
b1001 5
1%
1)
#318
0%
0)
#319
b1 ;
b1 #
b1 .
b10 :
08
01
b1 9
b0 7
b0 !
b0 *
b1 6
14
1/
b0 5
1%
1)
#320
0%
0)
#321
b1 7
b1 !
b1 *
b10 6
04
0/
b1 5
1%
1)
#322
0%
0)
#323
b10 7
b10 !
b10 *
b11 6
b10 5
1%
1)
#324
0%
0)
#325
b11 7
b11 !
b11 *
b100 6
b11 5
1%
1)
#326
0%
0)
#327
b100 7
b100 !
b100 *
b101 6
b100 5
1%
1)
#328
0%
0)
#329
b101 7
b101 !
b101 *
b110 6
b101 5
1%
1)
#330
0%
0)
#331
b110 7
b110 !
b110 *
b111 6
b110 5
1%
1)
#332
0%
0)
#333
b111 7
b111 !
b111 *
b1000 6
b111 5
1%
1)
#334
0%
0)
#335
b1000 7
b1000 !
b1000 *
b1001 6
b1000 5
1%
1)
#336
0%
0)
#337
b1001 7
b1001 !
b1001 *
b0 6
b1001 5
1%
1)
#338
0%
0)
#339
b10 ;
b10 #
b10 .
b11 :
b10 9
b0 7
b0 !
b0 *
b1 6
14
1/
b0 5
1%
1)
#340
0%
0)
#341
b1 7
b1 !
b1 *
b10 6
04
0/
b1 5
1%
1)
#342
0%
0)
#343
b10 7
b10 !
b10 *
b11 6
b10 5
1%
1)
#344
0%
0)
#345
b11 7
b11 !
b11 *
b100 6
b11 5
1%
1)
#346
0%
0)
#347
b100 7
b100 !
b100 *
b101 6
b100 5
1%
1)
#348
0%
0)
#349
b101 7
b101 !
b101 *
b110 6
b101 5
1%
1)
#350
0%
0)
#351
b110 7
b110 !
b110 *
b111 6
b110 5
1%
1)
#352
0%
0)
#353
b111 7
b111 !
b111 *
b1000 6
b111 5
1%
1)
#354
0%
0)
#355
b1000 7
b1000 !
b1000 *
b1001 6
b1000 5
1%
1)
#356
0%
0)
#357
b1001 7
b1001 !
b1001 *
b0 6
b1001 5
1%
1)
#358
0%
0)
#359
b11 ;
b11 #
b11 .
b100 :
b11 9
b0 7
b0 !
b0 *
b1 6
14
1/
b0 5
1%
1)
#360
0%
0)
#361
b1 7
b1 !
b1 *
b10 6
04
0/
b1 5
1%
1)
#362
0%
0)
#363
b10 7
b10 !
b10 *
b11 6
b10 5
1%
1)
#364
0%
0)
#365
b11 7
b11 !
b11 *
b100 6
b11 5
1%
1)
#366
0%
0)
#367
b100 7
b100 !
b100 *
b101 6
b100 5
1%
1)
#368
0%
0)
#369
b101 7
b101 !
b101 *
b110 6
b101 5
1%
1)
#370
0%
0)
#371
b110 7
b110 !
b110 *
b111 6
b110 5
1%
1)
#372
0%
0)
#373
b111 7
b111 !
b111 *
b1000 6
b111 5
1%
1)
#374
0%
0)
#375
b1000 7
b1000 !
b1000 *
b1001 6
b1000 5
1%
1)
#376
0%
0)
#377
b1001 7
b1001 !
b1001 *
b0 6
b1001 5
1%
1)
#378
0%
0)
#379
b100 ;
b100 #
b100 .
b101 :
b100 9
b0 7
b0 !
b0 *
b1 6
14
1/
b0 5
1%
1)
#380
0%
0)
#381
b1 7
b1 !
b1 *
b10 6
04
0/
b1 5
1%
1)
#382
0%
0)
#383
b10 7
b10 !
b10 *
b11 6
b10 5
1%
1)
#384
0%
0)
#385
b11 7
b11 !
b11 *
b100 6
b11 5
1%
1)
#386
0%
0)
#387
b100 7
b100 !
b100 *
b101 6
b100 5
1%
1)
#388
0%
0)
#389
b101 7
b101 !
b101 *
b110 6
b101 5
1%
1)
#390
0%
0)
#391
b110 7
b110 !
b110 *
b111 6
b110 5
1%
1)
#392
0%
0)
#393
b111 7
b111 !
b111 *
b1000 6
b111 5
1%
1)
#394
0%
0)
#395
b1000 7
b1000 !
b1000 *
b1001 6
b1000 5
1%
1)
#396
0%
0)
#397
b1001 7
b1001 !
b1001 *
b0 6
b1001 5
1%
1)
#398
0%
0)
#399
b101 ;
b101 #
b101 .
b110 :
b101 9
b0 7
b0 !
b0 *
b1 6
14
1/
b0 5
1%
1)
#400
0%
0)
#401
b1 7
b1 !
b1 *
b10 6
04
0/
b1 5
1%
1)
#402
0%
0)
#403
b10 7
b10 !
b10 *
b11 6
b10 5
1%
1)
#404
0%
0)
#405
b11 7
b11 !
b11 *
b100 6
b11 5
1%
1)
#406
0%
0)
#407
b100 7
b100 !
b100 *
b101 6
b100 5
1%
1)
#408
0%
0)
#409
b101 7
b101 !
b101 *
b110 6
b101 5
1%
1)
#410
0%
0)
#411
b110 7
b110 !
b110 *
b111 6
b110 5
1%
1)
#412
0%
0)
#413
b111 7
b111 !
b111 *
b1000 6
b111 5
1%
1)
#414
0%
0)
#415
b1000 7
b1000 !
b1000 *
b1001 6
b1000 5
1%
1)
#416
0%
0)
#417
b1001 7
b1001 !
b1001 *
b0 6
b1001 5
1%
1)
#418
0%
0)
#419
b110 ;
b110 #
b110 .
b111 :
b110 9
b0 7
b0 !
b0 *
b1 6
14
1/
b0 5
1%
1)
#420
0%
0)
#421
b1 7
b1 !
b1 *
b10 6
04
0/
b1 5
1%
1)
#422
0%
0)
#423
b10 7
b10 !
b10 *
b11 6
b10 5
1%
1)
#424
0%
0)
#425
b11 7
b11 !
b11 *
b100 6
b11 5
1%
1)
#426
0%
0)
#427
b100 7
b100 !
b100 *
b101 6
b100 5
1%
1)
#428
0%
0)
#429
b101 7
b101 !
b101 *
b110 6
b101 5
1%
1)
#430
0%
0)
#431
b110 7
b110 !
b110 *
b111 6
b110 5
1%
1)
#432
0%
0)
#433
b111 7
b111 !
b111 *
b1000 6
b111 5
1%
1)
#434
0%
0)
#435
b1000 7
b1000 !
b1000 *
b1001 6
b1000 5
1%
1)
#436
0%
0)
#437
b1001 7
b1001 !
b1001 *
b0 6
b1001 5
1%
1)
#438
0%
0)
#439
b111 ;
b111 #
b111 .
b1000 :
b111 9
b0 7
b0 !
b0 *
b1 6
14
1/
b0 5
1%
1)
#440
0%
0)
#441
b1 7
b1 !
b1 *
b10 6
04
0/
b1 5
1%
1)
#442
0%
0)
#443
b10 7
b10 !
b10 *
b11 6
b10 5
1%
1)
#444
0%
0)
#445
b11 7
b11 !
b11 *
b100 6
b11 5
1%
1)
#446
0%
0)
#447
b100 7
b100 !
b100 *
b101 6
b100 5
1%
1)
#448
0%
0)
#449
b101 7
b101 !
b101 *
b110 6
b101 5
1%
1)
#450
0%
0)
#451
b110 7
b110 !
b110 *
b111 6
b110 5
1%
1)
#452
0%
0)
#453
b111 7
b111 !
b111 *
b1000 6
b111 5
1%
1)
#454
0%
0)
#455
b1000 7
b1000 !
b1000 *
b1001 6
b1000 5
1%
1)
#456
0%
0)
#457
b1001 7
b1001 !
b1001 *
b0 6
b1001 5
1%
1)
#458
0%
0)
#459
b1000 ;
b1000 #
b1000 .
b1001 :
b1000 9
b0 7
b0 !
b0 *
b1 6
14
1/
b0 5
1%
1)
#460
0%
0)
#461
b1 7
b1 !
b1 *
b10 6
04
0/
b1 5
1%
1)
#462
0%
0)
#463
b10 7
b10 !
b10 *
b11 6
b10 5
1%
1)
#464
0%
0)
#465
b11 7
b11 !
b11 *
b100 6
b11 5
1%
1)
#466
0%
0)
#467
b100 7
b100 !
b100 *
b101 6
b100 5
1%
1)
#468
0%
0)
#469
b101 7
b101 !
b101 *
b110 6
b101 5
1%
1)
#470
0%
0)
#471
b110 7
b110 !
b110 *
b111 6
b110 5
1%
1)
#472
0%
0)
#473
b111 7
b111 !
b111 *
b1000 6
b111 5
1%
1)
#474
0%
0)
#475
b1000 7
b1000 !
b1000 *
b1001 6
b1000 5
1%
1)
#476
0%
0)
#477
b1001 7
b1001 !
b1001 *
b0 6
b1001 5
1%
1)
#478
0%
0)
#479
b1001 ;
b1001 #
b1001 .
b0 :
b1001 9
b0 7
b0 !
b0 *
b1 6
14
1/
b0 5
1%
1)
#480
0%
0)
#481
b1 7
b1 !
b1 *
b10 6
04
0/
b1 5
1%
1)
#482
0%
0)
#483
b10 7
b10 !
b10 *
b11 6
b10 5
1%
1)
#484
0%
0)
#485
b11 7
b11 !
b11 *
b100 6
b11 5
1%
1)
#486
0%
0)
#487
b100 7
b100 !
b100 *
b101 6
b100 5
1%
1)
#488
0%
0)
#489
b101 7
b101 !
b101 *
b110 6
b101 5
1%
1)
#490
0%
0)
#491
b110 7
b110 !
b110 *
b111 6
b110 5
1%
1)
#492
0%
0)
#493
b111 7
b111 !
b111 *
b1000 6
b111 5
1%
1)
#494
0%
0)
#495
b1000 7
b1000 !
b1000 *
b1001 6
b1000 5
1%
1)
#496
0%
0)
#497
b1001 7
b1001 !
b1001 *
b0 6
b1001 5
1%
1)
#498
0%
0)
#499
b10 ?
b10 $
b10 0
b11 >
b10 =
b0 ;
b0 #
b0 .
b1 :
18
11
b0 9
b0 7
b0 !
b0 *
b1 6
14
1/
b0 5
1%
1)
#500
0%
0)
#501
b1 7
b1 !
b1 *
b10 6
04
0/
b1 5
1%
1)
#502
0%
0)
#503
b10 7
b10 !
b10 *
b11 6
b10 5
1%
1)
#504
0%
0)
#505
b11 7
b11 !
b11 *
b100 6
b11 5
1%
1)
#506
0%
0)
#507
b100 7
b100 !
b100 *
b101 6
b100 5
1%
1)
#508
0%
0)
#509
b101 7
b101 !
b101 *
b110 6
b101 5
1%
1)
#510
0%
0)
#511
b110 7
b110 !
b110 *
b111 6
b110 5
1%
1)
#512
0%
0)
#513
b111 7
b111 !
b111 *
b1000 6
b111 5
1%
1)
#514
0%
0)
#515
b1000 7
b1000 !
b1000 *
b1001 6
b1000 5
1%
1)
#516
0%
0)
#517
b1001 7
b1001 !
b1001 *
b0 6
b1001 5
1%
1)
#518
0%
0)
#519
b1 ;
b1 #
b1 .
b10 :
08
01
b1 9
b0 7
b0 !
b0 *
b1 6
14
1/
b0 5
1%
1)
#520
0%
0)
#521
b1 7
b1 !
b1 *
b10 6
04
0/
b1 5
1%
1)
#522
0%
0)
#523
b10 7
b10 !
b10 *
b11 6
b10 5
1%
1)
#524
0%
0)
#525
b11 7
b11 !
b11 *
b100 6
b11 5
1%
1)
#526
0%
0)
#527
b100 7
b100 !
b100 *
b101 6
b100 5
1%
1)
#528
0%
0)
#529
b101 7
b101 !
b101 *
b110 6
b101 5
1%
1)
#530
0%
0)
#531
b110 7
b110 !
b110 *
b111 6
b110 5
1%
1)
#532
0%
0)
#533
b111 7
b111 !
b111 *
b1000 6
b111 5
1%
1)
#534
0%
0)
#535
b1000 7
b1000 !
b1000 *
b1001 6
b1000 5
1%
1)
#536
0%
0)
#537
b1001 7
b1001 !
b1001 *
b0 6
b1001 5
1%
1)
#538
0%
0)
#539
b10 ;
b10 #
b10 .
b11 :
b10 9
b0 7
b0 !
b0 *
b1 6
14
1/
b0 5
1%
1)
#540
0%
0)
#541
b1 7
b1 !
b1 *
b10 6
04
0/
b1 5
1%
1)
#542
0%
0)
#543
b10 7
b10 !
b10 *
b11 6
b10 5
1%
1)
#544
0%
0)
#545
b11 7
b11 !
b11 *
b100 6
b11 5
1%
1)
#546
0%
0)
#547
b100 7
b100 !
b100 *
b101 6
b100 5
1%
1)
#548
0%
0)
#549
b101 7
b101 !
b101 *
b110 6
b101 5
1%
1)
#550
0%
0)
#551
b110 7
b110 !
b110 *
b111 6
b110 5
1%
1)
#552
0%
0)
#553
b111 7
b111 !
b111 *
b1000 6
b111 5
1%
1)
#554
0%
0)
#555
b1000 7
b1000 !
b1000 *
b1001 6
b1000 5
1%
1)
#556
0%
0)
#557
b1001 7
b1001 !
b1001 *
b0 6
b1001 5
1%
1)
#558
0%
0)
#559
b11 ;
b11 #
b11 .
b100 :
b11 9
b0 7
b0 !
b0 *
b1 6
14
1/
b0 5
1%
1)
#560
0%
0)
#561
b1 7
b1 !
b1 *
b10 6
04
0/
b1 5
1%
1)
#562
0%
0)
#563
b10 7
b10 !
b10 *
b11 6
b10 5
1%
1)
#564
0%
0)
#565
b11 7
b11 !
b11 *
b100 6
b11 5
1%
1)
#566
0%
0)
