verilog/seqDetector/seqDetector111.v
module seqDetector111 (
  output out,
  input data, clk, reset
);

//Internal Variables
reg [1:0] cst, nst;
reg out;

parameter S0 = 2'b00,
  S1 = 2'b01,
  S2 = 2'b10,
  S3 = 2'b11; //after this, if 1 comes, out = 1

always @(cst or data)
begin
  case (cst)
    S0: if(data == 1'b1)
    begin
      nst = S1;
      out = 1'b0;
    end 
    else
    begin
      nst = S0;
      out = 1'b0;
    end 

    S1: if(data == 1'b1)
    begin
      nst = S3;
      out = 1'b0;
    end 
    else //data = 0;
    begin
      nst = S2;
      out = 1'b0;
    end 
    
    S2: if(data == 1'b1)
    begin
      nst = S1;
      out = 1'b0;
    end 
    else
    begin
      nst = S0;
      out = 1'b0;
    end 

    S3: if(data == 1'b1)
    begin
      nst = S3;
      out = 1'b1;
    end
    else 
    begin
      nst = S2;
      out = 1'b0;
    end

  default: nst = S0;
endcase
end

always @ (posedge clk)
begin
  begin
    if(reset)
      cst <= S0;
    else 
      cst <= nst;
  end
end

endmodule

verilog/seqDetector/seqDetector111_test.v
`include "seqDetector111.v"

module seqDetector111_test;
reg din, clk, reset;
wire out;

seqDetector111 uut(out, din,clk,reset);

initial begin
  din = 0; 
  reset = 1;
  clk = 0;
  $dumpfile("seq.vcd");
  $dumpvars(0,seqDetector111_test);
  forever begin
    #10 clk = ~clk;
  end 
end 

initial begin
  #20 reset = 0;
  #20 din = 0;
  #20 din = 1;
  #80 din = 0;
  #20 din = 0;
  #20 din = 0;
  #20 din = 0;
  #20 din = 0;

  //#30 reset = 1;
  #50 $finish;
end 

initial begin
  $monitor ($time,"clk: %b ",clk, "input: %b", din, " output: %b", out);
end

endmodule

verilog/seqDetector/seq.vcd
$date
	Sat May  9 21:32:24 2015
$end
$version
	Icarus Verilog
$end
$timescale
	1s
$end
$scope module seqDetector111_test $end
$var wire 1 ! out $end
$var reg 1 " clk $end
$var reg 1 # din $end
$var reg 1 $ reset $end
$scope module uut $end
$var wire 1 % clk $end
$var wire 1 & data $end
$var wire 1 ' reset $end
$var reg 2 ( cst [1:0] $end
$var reg 2 ) nst [1:0] $end
$var reg 1 * out $end
$upscope $end
$upscope $end
$enddefinitions $end
#0
$dumpvars
x*
b0 )
bx (
1'
0&
0%
1$
0#
0"
x!
$end
#10
0*
0!
b0 (
1"
1%
#20
0"
0%
0$
0'
#30
1"
1%
#40
0"
0%
#50
1"
1%
#60
b1 )
0"
0%
1#
1&
#70
b11 )
b1 (
1"
1%
#80
0"
0%
#90
1*
1!
b11 (
1"
1%
#100
0"
0%
#110
1"
1%
#120
0"
0%
#130
1"
1%
#140
0*
0!
b10 )
0"
0%
0#
0&
#150
b0 )
b10 (
1"
1%
#160
0"
0%
#170
b0 (
1"
1%
